Workbook

Sheet START HERE
A1: Control | B1: Current disposition
A2: Issue | B2: P14 Rev0 |25October2026 | Consolidated management-development package
A3: Baseline status | B3: NOT APPROVED; no actual NOA/progress/capacity or funding independently established
A4: Latest batch | B4: 68 supplied;67 opened;52 distinct contents;7 distinct contents without prior local hash match
A5: Transfer exception | B5: SHIVANSH ONGC Offshore Bridges - PRELIMINARY.pdf exceeds32MiB; not reviewed
A6: Prior batch | B6: P13:76 opened;21 distinct; XML207tasks/124links screened
A7: Authoritative use | B7: Management requirements/registers implemented here; technical design, actual execution and external approvals require their evidence
A8: Planning scenario | B8: 285activities,1Nov2026 assumed start; base finish6Apr2028, not an approved forecast
A9: Scenario meaning | B9: Explicit named resource sequencing; office/yard/offshore calendars; unverified engineering/productivity/supply inputs
A10: Financial use | B10: Blank inputs mean missing; no completed funding or EAC claim
A11: Source controls | B11: P8–P13 remain source evidence; P14 is consolidated management index and scenario, not a superseding contract
A12: Progress | B12: No actual work performed inferred from planning spreadsheets
A13: Revision | B13: Preserve uploaded originals; update P14 under change control

Sheet CEO Decisions
A1: Priority | B1: Decision | C1: Owner | D1: Required evidence | E1: Trigger | F1: Status
A2: P1 | B2: Confirm NOA/start, governing SCC/A3 and applicability | C2: Contracts | D2: Controlled issue list and actual award | E2: Before baseline | F2: OPEN
A3: P1 | B3: Freeze bridge scope and resolve MTO/bearing/load conflicts | C3: Engineering | D3: Survey, corrected MTO and design queries | E3: Before affected PO/AFC | F3: OPEN
A4: P1 | B4: Validate target feasibility and seasonal strategy | C4: Project Director | D4: Approved dates, capacity and supplier/vessel offers | E4: Before completion commitment | F4: OPEN
A5: P1 | B5: Fund full execution and commercial exposure | C5: Finance | D5: Priced estimate, term sheet and cash stress | E5: Before commitments | F5: OPEN
A6: P1 | B6: Nominate and verify delivery capacity | C6: Project Director | D6: People, design teams, fabrication/NDT/coating and marine commitments | E6: Before mobilisation | F6: OPEN
A7: P1 | B7: Approve stage-specific design/marine assurance | C7: Engineering/Marine | D7: Independent checked calculations and accepted procedures | E7: Before field release | F7: OPEN
A8: P2 | B8: Adopt progress/e-MB and completion boundaries | C8: Controls | D8: Contract weights, signed rules and turnover matrix | E8: Before first progress claim | F8: OPEN
A9: P2 | B9: Resolve large-file transfer exception | C9: Document Control | D9: Readable split PDF or equivalent verified source | E9: Before claiming complete source review | F9: OPEN

Sheet A-Z Execution Plan
A1: Code | B1: Workstream | C1: Accountable role | D1: Inputs | E1: Required procedure | F1: Acceptance evidence | G1: Control measure | H1: Source
A2: A | B2: Accountability and authority | C2: Project Director | D2: NOA/contract, scope split and corporate delegation | E2: Appoint named managers and deputies; record availability and competing commitments; establish RACI; set spending/change/technical-release authority; chair weekly integration review. | F2: Signed organisation/RACI and delegated-authority register | G2: Named accountable owner for each control; no unidentified release authority | H2: SCC1; Technical BEC5.2–5.4
A3: B | B3: Baseline and requirements | C3: Contracts Manager | D3: Tender, addenda/corrigenda, source drawing register | E3: Maintain clause-to-deliverable matrix; resolve SCC/GCC precedence using B-4; link revisions and deletions; isolate S&SRP references; freeze controlled scope by bridge and retain open discrepancies. | F3: Approved requirements and scope baseline; assumption/change log | G3: Every requirement has source, owner, verification and disposition | H3: P8–P12; CQ replies; B-4
A4: C | B4: Contract, qualification and compliance | C4: Contracts Manager | D4: Actual bidding route, experience evidence and amendments | E4: Check110MT/marine route and consortium exceptions; retain PM/qualifying main activity; obtain subcontract commitments; verify TPI authentication and valid accreditation; reconcile financial evidence; manage securities and integrity-pact disclosures. | F4: Qualification/compliance matrix and evidence bundle | G4: No unsupported bidder confirmations or expired verification evidence | H4: Technical BEC5; P9/P11
A5: D | B5: Design basis and survey | C5: Engineering Manager | D5: BRRP criteria, tender GAs and survey access | E5: Verify coordinates, elevations, spans, clearances, member sizes/thickness/loss, support movement, piping/cable loads and NDT; create controlled datums; close bearing/camber/load discrepancies; record later company instructions under change control. | F5: Accepted survey dossier and bridge-specific design basis | G5: Survey-derived geometry and load status visible on every engineering package | H5: CriteriaPartII; Corrigendum3 GCC2.3.6
A6: E | B6: Engineering and independent checking | C6: Engineering Manager | D6: Accepted survey, criteria, scope and discipline interfaces | E6: Analyse bridge and supporting platforms, members/joints, bearings, fatigue/VIV, preservice lifts/transport and temporary stages; iterate piping reactions; detail connections; perform independent check and comment closure; submit through controlled DCI. | F6: Checked calculations, interface reactions, design reports and accepted drawings | G6: No source-study utilisation ratio represented as new design proof | H6: C8; Combined1Annexure1; DesignCriteria
A7: F | B7: Fabrication drawings and AFC release | C7: Lead Structural Engineer | D7: Accepted mother analysis and verified geometry | E7: Issue source-to-detail mapping, shop GAs, member/cut lists, joint/weld maps, bearing/guides, padeyes/supports and temporary-stability details; apply source revisions and CRS; independent check then company/CA release as applicable. | F7: Signed bridge-specific release index with matching drawing/MTO/procedure revisions | G7: AFC status requires actual authorised approval and field-copy control | H7: C8 mother documents; Combined1 pp27–41
A8: G | B8: Geometry, MTO and weight control | C8: Quantity/Weight Engineer | D8: Released model/drawings and field verification | E8: Separate new bridge, strengthening, new landing, existing landing, demolition and finish quantities; resolve1MT/2m/1m² discrepancies; calculate member-length/plate/bolt/weld/coating MTO and wastage explicitly; track module dry/wet/rigging weights and COG. | F8: Traceable MTO revisions, reconciliation and verified module weight report | G8: No bulk tonnage substituted for lift weight, member BOM or coating area | H8: SOW quantity table; MTOIRT; Criteria weight/COG trigger
A9: H | B9: HSE and SIMOPS | C9: HSE Manager | D9: Workfront hazards, operating platform and vessel requirements | E9: Complete HIRA/JSA/PTW, isolation/LOTO, hot work, gas testing, work-at-height/rescue, dropped objects, scaffold/access, marine transfers, occupational exposure and emergency interfaces; train staff; issue certified PPE and validate work-start clearance. | F9: Approved HSE/SIMOPS plan, personnel matrix and permit packs | G9: Zero work starts without applicable permits, isolation and readiness evidence | H9: SCC7/8; PPElist; OISD155 applicability
A10: I | B10: Interface and operations management | C10: Interface Manager | D10: Platform operations, engineering and contractors | E10: Register structural/piping/electrical/instrument/telecom/firewater interfaces; agree outage and transfer sequence; assign tie-in owners; confirm access and emergency routes; track support reactions and dimensional tolerances; resolve NQO/NOQ naming. | F10: Signed interface agreements, outage windows and battery-limit register | G10: No unowned interface on lookahead or lift plan | H10: SCC1.7; Combined1/2/3
A11: J | B11: Joint inspections and quality assurance | C11: QA/QC Manager | D11: Project quality plan, codes, specifications and approved ITP | E11: Set inspection/hold/witness points; qualify welding and personnel; control heat/consumable traceability; calibrate instruments; inspect fit-up/weld/NDT/coating/dimensions; repair and close NCRs; issue releases and indexed records. | F11: ITP, qualification dossiers, inspection releases and NCR closure | G11: No concealed work or next-stage release through an unresolved hold point | H11: FS2009F; FS2005Rev9; C8
A12: K | B12: Key suppliers and procurement | C12: Procurement Manager | D12: Approved requisition, MTO, PS and compliant sources | E12: Package25 procurement scopes; RFQ and technical/commercial evaluation; verify SVL12.3 status/product/location, steel melt/pour/DVA and traceability; obtain PS approvals, place authorised PO, expedite and inspect; preserve vendor-data dependencies. | F12: PO/delivery/inspection register with quoted dates and evidence | G12: No unpriced allowance treated as commitment; no silent substitution | H12: SVL12.3 Combined3 pp261–341; Corr3; C8
... A27: Z | B27: Warranty, final account and lessons | C27: Project Director | D27: Acceptance terms, outstanding obligations and final payments | E27: Track defect liability/warranty and insurance/security releases; resolve claims and subcontract final accounts; retain integrity-pact/record obligations; archive controlled native/PDF data and access; close lessons and verify promised performance against outcomes. | F27: Contract closure certificate, release schedule and retained records | G27: Physical completion, financial closure and obligation expiry are separate dates | H27: IntegrityPact9; GCC/SCC governing periods

Sheet Source Coverage
A1: File | B1: SHA256 | C1: Prior exact matches | D1: Duplicate in batch | E1: Review disposition | F1: Local source
A2: Addendum.pdf | B2: 1742ad4dd672858b1ee148ba6e82b5d4594b3205a8db344d7631408e582a26fb | C2: 5 | E2: Hash/open checked; prior review reused | F2: /workspace/attachments/71d9446a-9284-4152-923c-f5c85a23c0f1/Addendum.pdf
A3: Addendum (1).pdf | B3: 1742ad4dd672858b1ee148ba6e82b5d4594b3205a8db344d7631408e582a26fb | C3: 5 | D3: Addendum.pdf | E3: Hash/open checked; prior review reused | F3: /workspace/attachments/62e4fd39-6c8f-4f77-88c2-7fbc71905567/Addendum (1).pdf
A4: Addendum_Structure_SOW.pdf | B4: 9720ca8546c67ef9cc4f44a8b4fb480de23da3eed38a6ca5dae2879de8c1485a | C4: 4 | E4: Hash/open checked; prior review reused | F4: /workspace/attachments/652f34f3-904c-4733-84f5-3badb6e94c6e/Addendum_Structure_SOW.pdf
A5: AddendumtoA3.pdf | B5: 191ca9ccafb391c57652a1e4b5831484c2a53765cf6d813b8bdc87dc1de3ce07 | C5: 2 | E5: Hash/open checked; prior review reused | F5: /workspace/attachments/b9a9de3b-b77d-49f1-8ff1-a0c7d55ca00b/AddendumtoA3.pdf
A6: Appendix A-9.pdf | B6: fea757b0e53dd170dbe9c645a10ddfe62eec08e2cfe6f151bbd0adf0bd4ed5e4 | C6: 2 | E6: Hash/open checked; prior review reused | F6: /workspace/attachments/67595e2c-856c-401e-833f-825f1401ae1e/Appendix A-9.pdf
A7: Appendix A-16 List of Agencies.pdf | B7: 09a642f2eb6a23c02a735be3d51b57db316f4d5697aff8e1db8c1ee7bacaa50a | C7: 2 | E7: Hash/open checked; prior review reused | F7: /workspace/attachments/2d2bfd9d-58b4-45b5-9b23-013e947fac6f/Appendix A-16 List of Agencies.pdf
A8: Appendix A-17.pdf | B8: 5d5cde215d0959b2e8126df4a2daf7edb4f91a7fc428146dda9d905c4aad6d6a | C8: 2 | E8: Hash/open checked; prior review reused | F8: /workspace/attachments/0cc90703-59ca-4d42-87f6-a21665d44d80/Appendix A-17.pdf
A9: Appendix A-11 Offshore SVL Revision 12.1.pdf | B9: 86d3ab9001388087d63075d5cde421a51a6d1f4c5857fda8e18f7459637f5381 | C9: 2 | E9: Hash/open checked; prior review reused | F9: /workspace/attachments/53ebe58d-28b5-4afe-a534-d4e5e90c0768/Appendix A-11 Offshore SVL Revision 12.1.pdf
A10: Appendix B-5.pdf | B10: 82222c4cdca2f142d619e139280c264c68085cca7444ad0f1152204a91f1bf3e | C10: 3 | E10: Hash/open checked; prior review reused | F10: /workspace/attachments/0f6b6e5d-3512-48b3-b967-7e0b5e54488c/Appendix B-5.pdf
A11: Appendix B-6.pdf | B11: dd4ce8688af1b3976c4fc752c9a19e4e14d43984c0e25733d11c6703d9919858 | C11: 2 | E11: Hash/open checked; prior review reused | F11: /workspace/attachments/4bee04c0-bc1c-43e2-9067-bf305f40553e/Appendix B-6.pdf
A12: Appendix C-9.pdf | B12: f20a85ca3a13c08e62bb18a41838d9e32910cd4f0d7c6b0ab0623df4ca9aeec5 | C12: 2 | E12: Hash/open checked; prior review reused | F12: /workspace/attachments/253ac71f-d176-432c-911f-60a8f984d59d/Appendix C-9.pdf
A13: Appendix C-8 DCI MCI.pdf | B13: 086b2f7837d09bc6320e2e0794f5b73fc7788b2cb9ecb5a08fa76836e2c97944 | C13: 2 | E13: Hash/open checked; prior review reused | F13: /workspace/attachments/5e260e43-5134-4a2f-a8df-817300abf68d/Appendix C-8 DCI MCI.pdf
A14: Appendix C-10.pdf | B14: 8f0b1be35e96cc0e953e8614b751f08a987dca4a9060c54319b231f113d7d2d7 | C14: 2 | E14: Hash/open checked; prior review reused | F14: /workspace/attachments/0c0ae9b7-787b-400e-bb17-d6a1c1a58cb8/Appendix C-10.pdf
A15: chart.pdf | B15: 30e8cf255d41edc9930b28ee4a2bea2c82dcd033222333c9a5e914ba0cb16b00 | C15: 0 | E15: Distinct content screened; discipline detail still required | F15: /workspace/attachments/790dcc2a-429d-42e1-9aa9-b5fc913b3310/chart.pdf
... A18: Corrigendum.pdf | B18: 02142550f5d609a6a2ffe4ed64d441eaa00540663cee661ed318446e6e19dea6 | C18: 1 | E18: Hash/open checked; prior review reused | F18: /workspace/attachments/a569298e-9b51-4a0a-865f-1a4350827b47/Corrigendum.pdf
A19: Combined_Addendum_1.pdf | B19: dfda0877c74c0745763a6d8eb0e8894014d27b22ec72c8f44955c933cadf1d65 | C19: 4 | D19: Combined_Addendum_1 (1).pdf | E19: Hash/open checked; prior review reused | F19: /workspace/attachments/24075e12-e392-4681-ac05-3e4aa60baea8/Combined_Addendum_1.pdf
A20: Corrigendum_1_BRRP.pdf | B20: 54977537e10a8249587ad2965eca04a057eaa45f932e6a229959bc3fa30ab7c4 | C20: 1 | E20: Hash/open checked; prior review reused | F20: /workspace/attachments/ce432d19-ef2c-4984-9b8f-1061008c14af/Corrigendum_1_BRRP.pdf
A21: Corrigendum_2.pdf | B21: cb996ec5837ec4dcfab1a55e4ffcb56248919a73d70cd53492d64d39a2a7b435 | C21: 1 | E21: Hash/open checked; prior review reused | F21: /workspace/attachments/6f519900-18e2-4842-a3a4-47eab8f9279c/Corrigendum_2.pdf
A22: Corrigendum_3.pdf | B22: e8a07f4059dcb9b81c1cc45b2ae60154c0c142999955b347d2c60133619656d7 | C22: 1 | E22: Hash/open checked; prior review reused | F22: /workspace/attachments/7932c206-c79d-4425-99a1-c83f9e788608/Corrigendum_3.pdf
A23: Corrigendum_4.pdf | B23: 623614acba28baadc68c22229c039399e9b4385c0945b787197b2dedaaa4acf4 | C23: 1 | E23: Hash/open checked; prior review reused | F23: /workspace/attachments/e3752b17-cf9c-472e-a3f1-cdcfb97319d9/Corrigendum_4.pdf
A24: CQ_replies_BRRP.pdf | B24: b006f3d20e7ae10d9800b1b9fabfb3104091b09878fcd6bb83b2f328e926df4a | C24: 1 | E24: Hash/open checked; prior review reused | F24: /workspace/attachments/dfc717ae-169c-4f98-a676-e4f9135968bb/CQ_replies_BRRP.pdf
A25: IP (1).pdf | B25: 8692fb4bca724408df3fe1ec8377faa678e6238f3fe14bb55fbc6ca4b8cdcf50 | C25: 2 | E25: Hash/open checked; prior review reused | F25: /workspace/attachments/86b20843-c858-4bbc-ba34-1eb21ae00511/IP (1).pdf
A26: Combined_Addendum_3.pdf | B26: 6d6369b880718f0b84da0776adc723d99eae59b591c8b5d45f1f0b2596b9d5b6 | C26: 1 | E26: Hash/open checked; prior review reused | F26: /workspace/attachments/1bc81107-8f35-4cbf-9221-83ba100de6ba/Combined_Addendum_3.pdf
A27: Design Criteria & Execution Methodology.pdf | B27: 179b05dabdb90971b5132d38f2a1aa755ce091b640b4e844fa7b0c9cc4a7e706 | C27: 2 | E27: Hash/open checked; prior review reused | F27: /workspace/attachments/88e427dd-3a5a-4b8d-bdbd-b42e46560820/Design Criteria & Execution Methodology.pdf
A28: IP.pdf | B28: 8692fb4bca724408df3fe1ec8377faa678e6238f3fe14bb55fbc6ca4b8cdcf50 | C28: 2 | D28: IP (1).pdf | E28: Hash/open checked; prior review reused | F28: /workspace/attachments/e09fff9b-4787-43dc-9837-32803d295090/IP.pdf
A29: Kits PPE List-BRRP.pdf | B29: 44e2e5f2214d741c15380702504a73ae00076ab5954bb6ce96011a1e06aed841 | C29: 1 | E29: Hash/open checked; prior review reused | F29: /workspace/attachments/fd490052-5a1c-457b-8b21-f994277ea8ec/Kits PPE List-BRRP.pdf
A30: Section 1.pdf | B30: 4396fb90c823805128145920d1348e69942a65e501773d80457a3b671e0f3641 | C30: 1 | E30: Hash/open checked; prior review reused | F30: /workspace/attachments/8da610f6-1801-4fe3-823d-e61a9d261607/Section 1.pdf
A31: Section 2.pdf | B31: 1d6c9da72ce45156e95586056c6d96a06da9563a9a27817dc77935d6fa470a7f | C31: 2 | E31: Hash/open checked; prior review reused | F31: /workspace/attachments/42bc04a5-aa70-4b68-8f62-6aa20791774b/Section 2.pdf
A32: MTO Drawings IRT.pdf | B32: 0a8a008d8bc139d05c75f83c52ba23d637c1f78926b7a19e4007297ac52485cb | C32: 1 | E32: Hash/open checked; prior review reused | F32: /workspace/attachments/6ac405c9-4cf3-4694-b74c-4bf32ee762e0/MTO Drawings IRT.pdf
A33: SHIVANSH ONGC Offshore Bridges - PRELIMINARY.xlsx | B33: caba714d2cc9b32ddf723228a57797a6e588463c0554ced81701982fcd7f7f20 | C33: 2 | E33: Hash/open checked; prior review reused | F33: /workspace/attachments/d9e9d456-d843-439f-9b8b-ba2073e00690/SHIVANSH ONGC Offshore Bridges - PRELIMINARY.xlsx
A34: SHIVANSH_360_Day_EPC_Scheduling_Control_Workbook.xlsx | B34: a4545c34bc3bfdf771c5918e9335e6b288626e024a5f517e4eb0ca7f6fe870ee | C34: 2 | E34: Hash/open checked; prior review reused | F34: /workspace/attachments/9d725d18-b225-48ae-b2c7-08bfdae07e20/SHIVANSH_360_Day_EPC_Scheduling_Control_Workbook.xlsx
A35: Shivansh_BRRPP_Integrated_Execution_Control.xlsx | B35: 2c64809e2cbab409c9897e19ee5b46768287708a1adb9f923457d03177f24c36 | C35: 2 | E35: Hash/open checked; prior review reused | F35: /workspace/attachments/e26488ad-6288-488e-9a57-e805e58d373d/Shivansh_BRRPP_Integrated_Execution_Control.xlsx
A36: Section 3.pdf | B36: 64146db7c46ea30fc3e5161cea2ce94bdb3435e4aefe05a81cfac0174c141108 | C36: 2 | E36: Hash/open checked; prior review reused | F36: /workspace/attachments/e8998ddd-f666-4184-8a06-cfe98fcee70d/Section 3.pdf
A37: Shivansh_BRRPP_Level3_P6_Preparation.xlsx | B37: 186a4f446d7691b5c726f32e8600482c7abde182ef9bbc7d11c07729e4706074 | C37: 2 | E37: Hash/open checked; prior review reused | F37: /workspace/attachments/5cd8d5fa-208f-4c83-8634-cc48ce45f232/Shivansh_BRRPP_Level3_P6_Preparation.xlsx
A38: Shivansh_BRRPP_P6_Activity_Import.csv | B38: cd3865f25e6d42bccc800bd4344e38816fdcf68c6dbbe63c26a0e76096f358d7 | C38: 1 | E38: Hash/open checked; prior review reused | F38: /workspace/attachments/93fa0f79-840c-4179-a70c-0453a58a772a/Shivansh_BRRPP_P6_Activity_Import.csv
A39: Shivansh_BRRPP_Stage4_Resource_Cost_Marine_Planning.xlsx | B39: 88adcd75ff58317d0215801c0cee35b3f8aa03b024e8acbd45382e8138db56f0 | C39: 1 | E39: Hash/open checked; prior review reused | F39: /workspace/attachments/7dc15993-36a3-4025-9400-43b50a6634fa/Shivansh_BRRPP_Stage4_Resource_Cost_Marine_Planning.xlsx
A40: Shivansh_BRRPP_Stage5_Integrated_Marine_Yard_Cost_P6.xlsx | B40: ac85c7dec0f9db25e971b0795623e465a92732bcc873ba6234bd21f485cc2036 | C40: 1 | E40: Hash/open checked; prior review reused | F40: /workspace/attachments/d26e8648-ae53-4e11-9b9e-462a8c2d2bf2/Shivansh_BRRPP_Stage5_Integrated_Marine_Yard_Cost_P6.xlsx
A41: Shivansh_BRRPP_Stage10_Resource_Feasibility (1).xlsx | B41: 44df6c84070a16804ad83487e7575ba1e99569a53e267c8e3da83ac9cfd59621 | C41: 3 | E41: Hash/open checked; prior review reused | F41: /workspace/attachments/eb12ce0c-0f11-4e8b-8f79-44bee2a5c743/Shivansh_BRRPP_Stage10_Resource_Feasibility (1).xlsx
A42: Shivansh_BRRPP_Stage10_Resource_Feasibility.xlsx | B42: 44df6c84070a16804ad83487e7575ba1e99569a53e267c8e3da83ac9cfd59621 | C42: 3 | D42: Shivansh_BRRPP_Stage10_Resource_Feasibility (1).xlsx | E42: Hash/open checked; prior review reused | F42: /workspace/attachments/af8b4024-34f5-445c-bf5a-6a9bdfb92b31/Shivansh_BRRPP_Stage10_Resource_Feasibility.xlsx
A43: Shivansh_BRRPP_Stage25_Cost_Cashflow_Model.xlsx | B43: a46229faa98cf1d94ebad3412394eda944398ea5f209b3da5b3fce3af1c0a7d6 | C43: 2 | E43: Hash/open checked; prior review reused | F43: /workspace/attachments/b862be55-df27-453e-abe6-771340b8533c/Shivansh_BRRPP_Stage25_Cost_Cashflow_Model.xlsx
A44: Shivansh_BRRPP_Stage26_Revenue_Cashflow_WorkingCapital (1).xlsx | B44: 9627644802f34de8ab9f44420ab6b7bad0437a6dbd5ea2a8dc0228d6f53bc422 | C44: 2 | E44: Hash/open checked; prior review reused | F44: /workspace/attachments/ecfd871a-db42-4242-b752-7c413a1065c2/Shivansh_BRRPP_Stage26_Revenue_Cashflow_WorkingCapital (1).xlsx
A45: Shivansh_BRRPP_Stage26_Revenue_Cashflow_WorkingCapital.xlsx | B45: 9627644802f34de8ab9f44420ab6b7bad0437a6dbd5ea2a8dc0228d6f53bc422 | C45: 2 | D45: Shivansh_BRRPP_Stage26_Revenue_Cashflow_WorkingCapital (1).xlsx | E45: Hash/open checked; prior review reused | F45: /workspace/attachments/f5e8b898-0da0-4e8c-a489-363b2fc2e689/Shivansh_BRRPP_Stage26_Revenue_Cashflow_WorkingCapital.xlsx
A46: Shivansh_BRRPP_Stage27_Integrated_EPC_Control.xlsx | B46: eaf6f3d25ff076225065d995c586af645d046c87ddc6bd205845e630ede8b4ef | C46: 0 | E46: Distinct content screened; discipline detail still required | F46: /workspace/attachments/c1f134e0-4c2b-483e-837f-7666380a5b4d/Shivansh_BRRPP_Stage27_Integrated_EPC_Control.xlsx
A47: Shivansh_BRRPP_Stage28_Level4_Execution_Schedule.xlsx | B47: 9614bca82b60f80b1f746d826905e951351c8630aed6ec1009a194b83f5fb747 | C47: 1 | E47: Hash/open checked; prior review reused | F47: /workspace/attachments/b5a48b69-16ae-4076-a4c5-9cf21de00369/Shivansh_BRRPP_Stage28_Level4_Execution_Schedule.xlsx
A48: Shivansh_BRRPP_Stage29_Resource_Recovery_Model.xlsx | B48: df1667a6a69dff2106ff4befae034044ceaf70a2876e448ba6561901adaa6f59 | C48: 1 | E48: Hash/open checked; prior review reused | F48: /workspace/attachments/5295e035-9004-4880-a5d5-8d42ef7d3efc/Shivansh_BRRPP_Stage29_Resource_Recovery_Model.xlsx
A49: Shivansh_BRRPP_Stage30_Workpack_Productivity_Control.xlsx | B49: cb59fab7d9a995acde11a16d7ab6a90dcc9c9c8b1b9f399439c8522dad76f678 | C49: 0 | E49: Distinct content screened; discipline detail still required | F49: /workspace/attachments/b58cc7bd-094f-4859-bbd6-71c815d50643/Shivansh_BRRPP_Stage30_Workpack_Productivity_Control.xlsx
A50: Shivansh_BRRPP_Stage31_Daily_Readiness_Production_System.xlsx | B50: 8b3de0f36bc9a4109bb5d9163df942dab56258ed44ae9b708e8308d1bc16cc5b | C50: 0 | E50: Distinct content screened; discipline detail still required | F50: /workspace/attachments/af5f377a-ecb4-4cc9-99de-17190c087166/Shivansh_BRRPP_Stage31_Daily_Readiness_Production_System.xlsx
A51: Shivansh_BRRPP_Stage32_Productivity_Forecast_Control (1).xlsx | B51: ac040e820fafb1c9806f6840331bf5c1272ba1df89f7b0ae87292b7aec99b7a0 | C51: 0 | E51: Distinct content screened; discipline detail still required | F51: /workspace/attachments/406d956f-fdc8-4096-8ed2-57dfdb944f4c/Shivansh_BRRPP_Stage32_Productivity_Forecast_Control (1).xlsx
A52: Shivansh_BRRPP_Stage33_Early_Warning_Recovery_Dashboard.xlsx | B52: 5bdcdaf794159caa61180384c6cdc30c01ff9485836f7c9b0693ea7e42f9b7cd | C52: 1 | E52: Hash/open checked; prior review reused | F52: /workspace/attachments/d957c5a5-a5e2-43c2-9ee2-d27b00e087ef/Shivansh_BRRPP_Stage33_Early_Warning_Recovery_Dashboard.xlsx
A53: Shivansh_BRRPP_Stage32_Productivity_Forecast_Control.xlsx | B53: ac040e820fafb1c9806f6840331bf5c1272ba1df89f7b0ae87292b7aec99b7a0 | C53: 0 | D53: Shivansh_BRRPP_Stage32_Productivity_Forecast_Control (1).xlsx | E53: Distinct content screened; discipline detail still required | F53: /workspace/attachments/87831bc1-2707-4555-8297-b539759e21d3/Shivansh_BRRPP_Stage32_Productivity_Forecast_Control.xlsx
A54: Shivansh_BRRPP_Stage35_90_Day_Mobilisation_Command_Plan.xlsx | B54: 5f19dcee0c81c6931459a5972763e6339eb036ac386518074246b415d1fc5be8 | C54: 1 | E54: Hash/open checked; prior review reused | F54: /workspace/attachments/f9408db4-29b9-482e-8e94-de2213453ddf/Shivansh_BRRPP_Stage35_90_Day_Mobilisation_Command_Plan.xlsx
A55: Shivansh_BRRPP_Stage34_Integrated_EPC_Control_Centre.xlsx | B55: bc4b4615629759d31ccc86ba1e4ecf532ee00d38596caad9a0da760c945362d6 | C55: 1 | E55: Hash/open checked; prior review reused | F55: /workspace/attachments/eb68b3fc-f253-47a2-b220-ff21f3834259/Shivansh_BRRPP_Stage34_Integrated_EPC_Control_Centre.xlsx
A56: SHIVANSH_EPC_Master_Plan_All_6_Volumes.zip | B56: d3d3ec37f51bb3dae0e4e52ff8af94dd9735bfcd341f12fb8debdb33c1354dd1 | C56: 1 | E56: Hash/open checked; prior review reused | F56: /workspace/attachments/37c20864-f5e3-4a94-85c7-cc94db455b87/SHIVANSH_EPC_Master_Plan_All_6_Volumes.zip
A57: SHIVANSH_EPC_Master_Plan_Volume_1 - Copy.docx | B57: 9b5eb6c4f99d251e612ffcc5acd598f69427282d0d12a4a1cf7a5c933ab3af6f | C57: 1 | E57: Hash/open checked; prior review reused | F57: /workspace/attachments/0518acf9-e4f9-4e04-8b74-c94b26366252/SHIVANSH_EPC_Master_Plan_Volume_1 - Copy.docx
A58: SHIVANSH_EPC_Master_Plan_Volume_1.docx | B58: 9b5eb6c4f99d251e612ffcc5acd598f69427282d0d12a4a1cf7a5c933ab3af6f | C58: 1 | D58: SHIVANSH_EPC_Master_Plan_Volume_1 - Copy.docx | E58: Hash/open checked; prior review reused | F58: /workspace/attachments/27497066-85c1-47c6-93db-8c616fd503c6/SHIVANSH_EPC_Master_Plan_Volume_1.docx
A59: SHIVANSH_EPC_Master_Plan_Volume_2 - Copy (2) - Copy.docx | B59: ce3642b042ad5b0013de702d9361b1759e5c8e3fbd12839ba2a65de97cf17533 | C59: 0 | E59: Distinct content screened; discipline detail still required | F59: /workspace/attachments/44c92e4b-5800-43ac-97df-48e11ac8d63b/SHIVANSH_EPC_Master_Plan_Volume_2 - Copy (2) - Copy.docx
A60: SHIVANSH_EPC_Master_Plan_Volume_2 - Copy (2).docx | B60: ce3642b042ad5b0013de702d9361b1759e5c8e3fbd12839ba2a65de97cf17533 | C60: 0 | D60: SHIVANSH_EPC_Master_Plan_Volume_2 - Copy (2) - Copy.docx | E60: Distinct content screened; discipline detail still required | F60: /workspace/attachments/4448d91b-75d1-4b69-99e3-1c2b1a86b75c/SHIVANSH_EPC_Master_Plan_Volume_2 - Copy (2).docx
A61: SHIVANSH_EPC_Master_Plan_Volume_2 - Copy.docx | B61: ce3642b042ad5b0013de702d9361b1759e5c8e3fbd12839ba2a65de97cf17533 | C61: 0 | D61: SHIVANSH_EPC_Master_Plan_Volume_2 - Copy (2) - Copy.docx | E61: Distinct content screened; discipline detail still required | F61: /workspace/attachments/64000d7c-788f-4100-8ae7-a2015a09c0d2/SHIVANSH_EPC_Master_Plan_Volume_2 - Copy.docx
A62: SHIVANSH_EPC_Master_Plan_Volume_3 - Copy - Copy - Copy.docx | B62: c477c827f9aa7be3bb8ee77c5e4ae906d13836dac27daee468518f4ff869c526 | C62: 0 | E62: Distinct content screened; discipline detail still required | F62: /workspace/attachments/8a6d78e8-4db2-4f46-96a6-9eae1c917653/SHIVANSH_EPC_Master_Plan_Volume_3 - Copy - Copy - Copy.docx
A63: SHIVANSH_EPC_Master_Plan_Volume_3 - Copy - Copy (2).docx | B63: c477c827f9aa7be3bb8ee77c5e4ae906d13836dac27daee468518f4ff869c526 | C63: 0 | D63: SHIVANSH_EPC_Master_Plan_Volume_3 - Copy - Copy - Copy.docx | E63: Distinct content screened; discipline detail still required | F63: /workspace/attachments/3e570754-b37e-4c16-a5f3-5fefb1847ca2/SHIVANSH_EPC_Master_Plan_Volume_3 - Copy - Copy (2).docx
A64: SHIVANSH_EPC_Master_Plan_Volume_2.docx | B64: ce3642b042ad5b0013de702d9361b1759e5c8e3fbd12839ba2a65de97cf17533 | C64: 0 | D64: SHIVANSH_EPC_Master_Plan_Volume_2 - Copy (2) - Copy.docx | E64: Distinct content screened; discipline detail still required | F64: /workspace/attachments/f8a5dc0c-f647-4318-be98-22b2f8f4b7a6/SHIVANSH_EPC_Master_Plan_Volume_2.docx
A65: SHIVANSH_EPC_Master_Plan_Volume_3 - Copy - Copy.docx | B65: c477c827f9aa7be3bb8ee77c5e4ae906d13836dac27daee468518f4ff869c526 | C65: 0 | D65: SHIVANSH_EPC_Master_Plan_Volume_3 - Copy - Copy - Copy.docx | E65: Distinct content screened; discipline detail still required | F65: /workspace/attachments/ee92c4a0-d95c-41b3-a1cc-8581af1ee023/SHIVANSH_EPC_Master_Plan_Volume_3 - Copy - Copy.docx
A66: SHIVANSH_EPC_Master_Plan_Volume_3 - Copy (2) - Copy.docx | B66: c477c827f9aa7be3bb8ee77c5e4ae906d13836dac27daee468518f4ff869c526 | C66: 0 | D66: SHIVANSH_EPC_Master_Plan_Volume_3 - Copy - Copy - Copy.docx | E66: Distinct content screened; discipline detail still required | F66: /workspace/attachments/7a21c556-65d6-482c-a802-ed369b4d4df9/SHIVANSH_EPC_Master_Plan_Volume_3 - Copy (2) - Copy.docx
A67: SHIVANSH_EPC_Master_Plan_Volume_3 - Copy (2).docx | B67: c477c827f9aa7be3bb8ee77c5e4ae906d13836dac27daee468518f4ff869c526 | C67: 0 | D67: SHIVANSH_EPC_Master_Plan_Volume_3 - Copy - Copy - Copy.docx | E67: Distinct content screened; discipline detail still required | F67: /workspace/attachments/6ad32486-2ba2-4baf-a610-d11053809828/SHIVANSH_EPC_Master_Plan_Volume_3 - Copy (2).docx
A68: SHIVANSH_EPC_Master_Plan_Volume_3 - Copy (3).docx | B68: c477c827f9aa7be3bb8ee77c5e4ae906d13836dac27daee468518f4ff869c526 | C68: 0 | D68: SHIVANSH_EPC_Master_Plan_Volume_3 - Copy - Copy - Copy.docx | E68: Distinct content screened; discipline detail still required | F68: /workspace/attachments/cde4c99b-9f2d-43d9-bef9-3fdd909b5310/SHIVANSH_EPC_Master_Plan_Volume_3 - Copy (3).docx
A69: PRELIMINARY.pdf | C69: 0 | E69: file exceeds the executor transfer limit of 32 MiB

Sheet Earlier P13 Coverage
A1: File | B1: SHA256 | C1: Prior exact matches | D1: Duplicate | E1: Disposition
A2: SHIVANSH_EPC_Master_Plan_Volume_5 - Copy - Copy - Copy.docx | B2: 780b6b86fcd5d34d71bf2cc18548d62a298cee1a296ad7636365ee10c2ff9226 | C2: 0 | E2: Duplicate comparison; P13 content/XML screening
A3: SHIVANSH_EPC_Master_Plan_Volume_4.docx | B3: fdbbcaf61b89b33696bc164ebf7c866c81f4cac5d9ee8bda20b38c00087f038f | C3: 0 | E3: Duplicate comparison; P13 content/XML screening
A4: SHIVANSH_EPC_Master_Plan_Volume_4 - Copy.docx | B4: fdbbcaf61b89b33696bc164ebf7c866c81f4cac5d9ee8bda20b38c00087f038f | C4: 0 | D4: SHIVANSH_EPC_Master_Plan_Volume_4.docx | E4: Duplicate comparison; P13 content/XML screening
A5: SHIVANSH_EPC_Master_Plan_Volume_5 - Copy (2).docx | B5: 780b6b86fcd5d34d71bf2cc18548d62a298cee1a296ad7636365ee10c2ff9226 | C5: 0 | D5: SHIVANSH_EPC_Master_Plan_Volume_5 - Copy - Copy - Copy.docx | E5: Duplicate comparison; P13 content/XML screening
A6: SHIVANSH_EPC_Master_Plan_Volume_5 - Copy - Copy.docx | B6: 780b6b86fcd5d34d71bf2cc18548d62a298cee1a296ad7636365ee10c2ff9226 | C6: 0 | D6: SHIVANSH_EPC_Master_Plan_Volume_5 - Copy - Copy - Copy.docx | E6: Duplicate comparison; P13 content/XML screening
A7: SHIVANSH_EPC_Master_Plan_Volume_5 - Copy (2) - Copy.docx | B7: 780b6b86fcd5d34d71bf2cc18548d62a298cee1a296ad7636365ee10c2ff9226 | C7: 0 | D7: SHIVANSH_EPC_Master_Plan_Volume_5 - Copy - Copy - Copy.docx | E7: Duplicate comparison; P13 content/XML screening
A8: SHIVANSH_EPC_Master_Plan_Volume_5 - Copy.docx | B8: 780b6b86fcd5d34d71bf2cc18548d62a298cee1a296ad7636365ee10c2ff9226 | C8: 0 | D8: SHIVANSH_EPC_Master_Plan_Volume_5 - Copy - Copy - Copy.docx | E8: Duplicate comparison; P13 content/XML screening
A9: SHIVANSH_EPC_Master_Plan_Volume_5.docx | B9: 780b6b86fcd5d34d71bf2cc18548d62a298cee1a296ad7636365ee10c2ff9226 | C9: 0 | D9: SHIVANSH_EPC_Master_Plan_Volume_5 - Copy - Copy - Copy.docx | E9: Duplicate comparison; P13 content/XML screening
A10: SHIVANSH_EPC_Master_Plan_Volume_6 - Copy - Copy.docx | B10: 210c62c17a32f6b0545c512e9ae7d145c318845c51edd1ab2af106cd7ba3d79e | C10: 0 | E10: Duplicate comparison; P13 content/XML screening
A11: SHIVANSH_EPC_Master_Plan_Volume_6.docx | B11: 210c62c17a32f6b0545c512e9ae7d145c318845c51edd1ab2af106cd7ba3d79e | C11: 0 | D11: SHIVANSH_EPC_Master_Plan_Volume_6 - Copy - Copy.docx | E11: Duplicate comparison; P13 content/XML screening
A12: SHIVANSH_PreAward_207_Activities_ProjectLibre_Import.xml | B12: d3f7199e9981a38001856c7fc4dfacadcc7158efe4310febc1c9040489b5bcb2 | C12: 1 | E12: Duplicate comparison; P13 content/XML screening
A13: SHIVANSH_EPC_Master_Plan_Volume_6 - Copy.docx | B13: 210c62c17a32f6b0545c512e9ae7d145c318845c51edd1ab2af106cd7ba3d79e | C13: 0 | D13: SHIVANSH_EPC_Master_Plan_Volume_6 - Copy - Copy.docx | E13: Duplicate comparison; P13 content/XML screening
A14: SOW & Bridge Report Combined - Copy - Copy.pdf | B14: 1dd8c329d410a7ea7f6b497d8c0fb230e23feaeabcd80964503bdb530236770a | C14: 4 | E14: Duplicate comparison; P13 content/XML screening
A15: SOW & Bridge Report Combined - Copy.pdf | B15: 1dd8c329d410a7ea7f6b497d8c0fb230e23feaeabcd80964503bdb530236770a | C15: 4 | D15: SOW & Bridge Report Combined - Copy - Copy.pdf | E15: Duplicate comparison; P13 content/XML screening
A16: SOW & Bridge Report Combined (3) - Copy - Copy.pdf | B16: 1dd8c329d410a7ea7f6b497d8c0fb230e23feaeabcd80964503bdb530236770a | C16: 4 | D16: SOW & Bridge Report Combined - Copy - Copy.pdf | E16: Duplicate comparison; P13 content/XML screening
A17: SOW & Bridge Report Combined (3) - Copy.pdf | B17: 1dd8c329d410a7ea7f6b497d8c0fb230e23feaeabcd80964503bdb530236770a | C17: 4 | D17: SOW & Bridge Report Combined - Copy - Copy.pdf | E17: Duplicate comparison; P13 content/XML screening
A18: SOW & Bridge Report Combined (3).pdf | B18: 1dd8c329d410a7ea7f6b497d8c0fb230e23feaeabcd80964503bdb530236770a | C18: 4 | D18: SOW & Bridge Report Combined - Copy - Copy.pdf | E18: Duplicate comparison; P13 content/XML screening
A19: SOW & Bridge Report Combined.pdf | B19: 1dd8c329d410a7ea7f6b497d8c0fb230e23feaeabcd80964503bdb530236770a | C19: 4 | D19: SOW & Bridge Report Combined - Copy - Copy.pdf | E19: Duplicate comparison; P13 content/XML screening
A20: Specification Combined - Copy - Copy.pdf | B20: fcb66cef439b04510b11d0225c2c7327e70a7aeaa8476651e9adc4329a5095eb | C20: 4 | E20: Duplicate comparison; P13 content/XML screening
A21: Specification Combined - Copy - Copy - Copy.pdf | B21: fcb66cef439b04510b11d0225c2c7327e70a7aeaa8476651e9adc4329a5095eb | C21: 4 | D21: Specification Combined - Copy - Copy.pdf | E21: Duplicate comparison; P13 content/XML screening
A22: Specification Combined - Copy.pdf | B22: fcb66cef439b04510b11d0225c2c7327e70a7aeaa8476651e9adc4329a5095eb | C22: 4 | D22: Specification Combined - Copy - Copy.pdf | E22: Duplicate comparison; P13 content/XML screening
A23: Specification Combined - Copy (2) - Copy.pdf | B23: fcb66cef439b04510b11d0225c2c7327e70a7aeaa8476651e9adc4329a5095eb | C23: 4 | D23: Specification Combined - Copy - Copy.pdf | E23: Duplicate comparison; P13 content/XML screening
A24: Specification Combined - Copy (2).pdf | B24: fcb66cef439b04510b11d0225c2c7327e70a7aeaa8476651e9adc4329a5095eb | C24: 4 | D24: Specification Combined - Copy - Copy.pdf | E24: Duplicate comparison; P13 content/XML screening
A25: TBOextension050526 - Copy - Copy - Copy.pdf | B25: 9b7cf7505a87a3743ad2da609f7cd2357ad0717a20aefae32c1baf4196876011 | C25: 1 | E25: Duplicate comparison; P13 content/XML screening
A26: Specification Combined.pdf | B26: fcb66cef439b04510b11d0225c2c7327e70a7aeaa8476651e9adc4329a5095eb | C26: 4 | D26: Specification Combined - Copy - Copy.pdf | E26: Duplicate comparison; P13 content/XML screening
A27: TBOextension050526 - Copy - Copy.pdf | B27: 9b7cf7505a87a3743ad2da609f7cd2357ad0717a20aefae32c1baf4196876011 | C27: 1 | D27: TBOextension050526 - Copy - Copy - Copy.pdf | E27: Duplicate comparison; P13 content/XML screening
A28: TBOextension050526 - Copy (2).pdf | B28: 9b7cf7505a87a3743ad2da609f7cd2357ad0717a20aefae32c1baf4196876011 | C28: 1 | D28: TBOextension050526 - Copy - Copy - Copy.pdf | E28: Duplicate comparison; P13 content/XML screening
A29: TBOextension050526 - Copy (2) - Copy.pdf | B29: 9b7cf7505a87a3743ad2da609f7cd2357ad0717a20aefae32c1baf4196876011 | C29: 1 | D29: TBOextension050526 - Copy - Copy - Copy.pdf | E29: Duplicate comparison; P13 content/XML screening
A30: TBOextension050526 - Copy.pdf | B30: 9b7cf7505a87a3743ad2da609f7cd2357ad0717a20aefae32c1baf4196876011 | C30: 1 | D30: TBOextension050526 - Copy - Copy - Copy.pdf | E30: Duplicate comparison; P13 content/XML screening
A31: TBOextension050526.pdf | B31: 9b7cf7505a87a3743ad2da609f7cd2357ad0717a20aefae32c1baf4196876011 | C31: 1 | D31: TBOextension050526 - Copy - Copy - Copy.pdf | E31: Duplicate comparison; P13 content/XML screening
A32: TBOextension090626 - Copy - Copy.pdf | B32: 916fdbeecc51c1c44bb20aa3cbc1a8ef3a246fbb0e7c38d605007f72d24021a1 | C32: 2 | E32: Duplicate comparison; P13 content/XML screening
A33: TBOextension090626 - Copy.pdf | B33: 916fdbeecc51c1c44bb20aa3cbc1a8ef3a246fbb0e7c38d605007f72d24021a1 | C33: 2 | D33: TBOextension090626 - Copy - Copy.pdf | E33: Duplicate comparison; P13 content/XML screening
A34: TBOextension090626 - Copy - Copy - Copy.pdf | B34: 916fdbeecc51c1c44bb20aa3cbc1a8ef3a246fbb0e7c38d605007f72d24021a1 | C34: 2 | D34: TBOextension090626 - Copy - Copy.pdf | E34: Duplicate comparison; P13 content/XML screening
A35: TBOextension090626.pdf | B35: 916fdbeecc51c1c44bb20aa3cbc1a8ef3a246fbb0e7c38d605007f72d24021a1 | C35: 2 | D35: TBOextension090626 - Copy - Copy.pdf | E35: Duplicate comparison; P13 content/XML screening
A36: TBOextension250526 - Copy - Copy - Copy.pdf | B36: c74098b236b0b059fe9cd539b814bf6838c586cd3a2701d63f41a0d579b7494b | C36: 1 | E36: Duplicate comparison; P13 content/XML screening
A37: TBOextension250526 - Copy - Copy.pdf | B37: c74098b236b0b059fe9cd539b814bf6838c586cd3a2701d63f41a0d579b7494b | C37: 1 | D37: TBOextension250526 - Copy - Copy - Copy.pdf | E37: Duplicate comparison; P13 content/XML screening
A38: TBOextension250526 - Copy.pdf | B38: c74098b236b0b059fe9cd539b814bf6838c586cd3a2701d63f41a0d579b7494b | C38: 1 | D38: TBOextension250526 - Copy - Copy - Copy.pdf | E38: Duplicate comparison; P13 content/XML screening
A39: TBOextension250526.pdf | B39: c74098b236b0b059fe9cd539b814bf6838c586cd3a2701d63f41a0d579b7494b | C39: 1 | D39: TBOextension250526 - Copy - Copy - Copy.pdf | E39: Duplicate comparison; P13 content/XML screening
A40: Technical_SCC - Copy - Copy.pdf | B40: c954759fb14588581784c894f9ffe949760a608217a75f73809b4eefa937ee17 | C40: 9 | E40: Duplicate comparison; P13 content/XML screening
A41: Technical_SCC - Copy - Copy - Copy.pdf | B41: c954759fb14588581784c894f9ffe949760a608217a75f73809b4eefa937ee17 | C41: 9 | D41: Technical_SCC - Copy - Copy.pdf | E41: Duplicate comparison; P13 content/XML screening
A42: Technical_SCC - Copy.pdf | B42: c954759fb14588581784c894f9ffe949760a608217a75f73809b4eefa937ee17 | C42: 9 | D42: Technical_SCC - Copy - Copy.pdf | E42: Duplicate comparison; P13 content/XML screening
A43: Technical_SCC (1) - Copy - Copy - Copy.pdf | B43: c954759fb14588581784c894f9ffe949760a608217a75f73809b4eefa937ee17 | C43: 9 | D43: Technical_SCC - Copy - Copy.pdf | E43: Duplicate comparison; P13 content/XML screening
A44: Technical_SCC (1) - Copy - Copy.pdf | B44: c954759fb14588581784c894f9ffe949760a608217a75f73809b4eefa937ee17 | C44: 9 | D44: Technical_SCC - Copy - Copy.pdf | E44: Duplicate comparison; P13 content/XML screening
A45: Technical_SCC (1) - Copy.pdf | B45: c954759fb14588581784c894f9ffe949760a608217a75f73809b4eefa937ee17 | C45: 9 | D45: Technical_SCC - Copy - Copy.pdf | E45: Duplicate comparison; P13 content/XML screening
A46: Technical_SCC (2) - Copy - Copy - Copy.pdf | B46: c954759fb14588581784c894f9ffe949760a608217a75f73809b4eefa937ee17 | C46: 9 | D46: Technical_SCC - Copy - Copy.pdf | E46: Duplicate comparison; P13 content/XML screening
A47: Technical_SCC (2) - Copy - Copy.pdf | B47: c954759fb14588581784c894f9ffe949760a608217a75f73809b4eefa937ee17 | C47: 9 | D47: Technical_SCC - Copy - Copy.pdf | E47: Duplicate comparison; P13 content/XML screening
A48: Technical_SCC (1).pdf | B48: c954759fb14588581784c894f9ffe949760a608217a75f73809b4eefa937ee17 | C48: 9 | D48: Technical_SCC - Copy - Copy.pdf | E48: Duplicate comparison; P13 content/XML screening
A49: Technical_SCC (2) - Copy.pdf | B49: c954759fb14588581784c894f9ffe949760a608217a75f73809b4eefa937ee17 | C49: 9 | D49: Technical_SCC - Copy - Copy.pdf | E49: Duplicate comparison; P13 content/XML screening
A50: Technical_SCC (2).pdf | B50: c954759fb14588581784c894f9ffe949760a608217a75f73809b4eefa937ee17 | C50: 9 | D50: Technical_SCC - Copy - Copy.pdf | E50: Duplicate comparison; P13 content/XML screening
A51: Technical_SCC (3) - Copy - Copy - Copy.pdf | B51: c954759fb14588581784c894f9ffe949760a608217a75f73809b4eefa937ee17 | C51: 9 | D51: Technical_SCC - Copy - Copy.pdf | E51: Duplicate comparison; P13 content/XML screening
A52: Technical_SCC (3) - Copy - Copy.pdf | B52: c954759fb14588581784c894f9ffe949760a608217a75f73809b4eefa937ee17 | C52: 9 | D52: Technical_SCC - Copy - Copy.pdf | E52: Duplicate comparison; P13 content/XML screening
... A54: Technical_SCC.pdf | B54: c954759fb14588581784c894f9ffe949760a608217a75f73809b4eefa937ee17 | C54: 9 | D54: Technical_SCC - Copy - Copy.pdf | E54: Duplicate comparison; P13 content/XML screening
A55: Tendernotice_1 - Copy - Copy - Copy.pdf | B55: 97463997491227dbddeffd8bdd92d82f3d497b88b99227b05a55b03111dda78d | C55: 11 | E55: Duplicate comparison; P13 content/XML screening
A56: Technical_SCC (3).pdf | B56: c954759fb14588581784c894f9ffe949760a608217a75f73809b4eefa937ee17 | C56: 9 | D56: Technical_SCC - Copy - Copy.pdf | E56: Duplicate comparison; P13 content/XML screening
A57: Tendernotice_1 (1) - Copy - Copy - Copy.pdf | B57: 97463997491227dbddeffd8bdd92d82f3d497b88b99227b05a55b03111dda78d | C57: 11 | D57: Tendernotice_1 - Copy - Copy - Copy.pdf | E57: Duplicate comparison; P13 content/XML screening
A58: Tendernotice_1 - Copy.pdf | B58: 97463997491227dbddeffd8bdd92d82f3d497b88b99227b05a55b03111dda78d | C58: 11 | D58: Tendernotice_1 - Copy - Copy - Copy.pdf | E58: Duplicate comparison; P13 content/XML screening
A59: Tendernotice_1 - Copy - Copy.pdf | B59: 97463997491227dbddeffd8bdd92d82f3d497b88b99227b05a55b03111dda78d | C59: 11 | D59: Tendernotice_1 - Copy - Copy - Copy.pdf | E59: Duplicate comparison; P13 content/XML screening
A60: Tendernotice_1 (1) - Copy - Copy.pdf | B60: 97463997491227dbddeffd8bdd92d82f3d497b88b99227b05a55b03111dda78d | C60: 11 | D60: Tendernotice_1 - Copy - Copy - Copy.pdf | E60: Duplicate comparison; P13 content/XML screening
A61: Tendernotice_1 (1).pdf | B61: 97463997491227dbddeffd8bdd92d82f3d497b88b99227b05a55b03111dda78d | C61: 11 | D61: Tendernotice_1 - Copy - Copy - Copy.pdf | E61: Duplicate comparison; P13 content/XML screening
A62: Tendernotice_1 (1) - Copy.pdf | B62: 97463997491227dbddeffd8bdd92d82f3d497b88b99227b05a55b03111dda78d | C62: 11 | D62: Tendernotice_1 - Copy - Copy - Copy.pdf | E62: Duplicate comparison; P13 content/XML screening
A63: Tendernotice_1.pdf | B63: 97463997491227dbddeffd8bdd92d82f3d497b88b99227b05a55b03111dda78d | C63: 11 | D63: Tendernotice_1 - Copy - Copy - Copy.pdf | E63: Duplicate comparison; P13 content/XML screening
A64: Vol I _PartV_Appendix A-3 Price Schedule.xlsx | B64: 7b4e2c5849fc2b293e4de333dd3bb7b9893702fce99f93d01d637308b1d397a6 | C64: 2 | E64: Duplicate comparison; P13 content/XML screening
A65: Vol I _PartV_Appendix A-10 MPF.xlsx | B65: 3e1398fa91d52a60c14f78ba4aaccd1e2a3b90b8cc5046dc980561a45e712aa9 | C65: 2 | E65: Duplicate comparison; P13 content/XML screening
A66: ticket.pdf | B66: 207b0d36e2def3753e5b65b9c2432176235741f6f9d03713f2e532068c295bea | C66: 0 | E66: Duplicate comparison; P13 content/XML screening
A67: Vol I _PartVA_BRS.xlsx | B67: 872ba27d634dc202597837a32971bafa19c0eb54ac151f7c86f64bccd1d5d897 | C67: 1 | E67: Duplicate comparison; P13 content/XML screening
A68: Vol I_ Part III Appendices.docx | B68: c1ef1672214f304f856d1a3bdb5f1a3c4d685f00e484907e5bc826d46155ca7f | C68: 2 | E68: Duplicate comparison; P13 content/XML screening
A69: Vol I_PartIV_BEC - Copy.docx | B69: df1674f7946d9f62bfc169251d43ad05ee75549001c0d460408055e43b9818b2 | C69: 3 | E69: Duplicate comparison; P13 content/XML screening
A70: Vol I_PartIV_BEC.docx | B70: df1674f7946d9f62bfc169251d43ad05ee75549001c0d460408055e43b9818b2 | C70: 3 | D70: Vol I_PartIV_BEC - Copy.docx | E70: Duplicate comparison; P13 content/XML screening
A71: Vol I_PartIVA_BidderGTE.xlsx | B71: 73b9c45b583b3612ee2b8bcb5a0f95cfad5392979d3d697c8f9ff3c1664d5e02 | C71: 2 | E71: Duplicate comparison; P13 content/XML screening
A72: Vol I_PartIVA_BidderGTE - Copy.xlsx | B72: 73b9c45b583b3612ee2b8bcb5a0f95cfad5392979d3d697c8f9ff3c1664d5e02 | C72: 2 | D72: Vol I_PartIVA_BidderGTE.xlsx | E72: Duplicate comparison; P13 content/XML screening
A73: Vol_I_PartIV_ Technical BEC - Copy.pdf | B73: d5548eb59f55cf6504d770c44e2dcd42b42392eb71541f36a742df9b089e3a7c | C73: 3 | E73: Duplicate comparison; P13 content/XML screening
A74: Vol-I I ITB - Copy.docx | B74: 61033c9e7a297215977bdbf88dd81b3bca8073d17e7ae88f2ae7b57ce1fd58ae | C74: 3 | E74: Duplicate comparison; P13 content/XML screening
A75: Vol_I_PartIV_ Technical BEC.pdf | B75: d5548eb59f55cf6504d770c44e2dcd42b42392eb71541f36a742df9b089e3a7c | C75: 3 | D75: Vol_I_PartIV_ Technical BEC - Copy.pdf | E75: Duplicate comparison; P13 content/XML screening
A76: Vol-I-II GCC - Copy.docx | B76: 78d8130c8aab9b96e9dad2584cb6c30be370c72dd71f154df103eb238b08f4a1 | C76: 3 | E76: Duplicate comparison; P13 content/XML screening
A77: Vol-I I ITB.docx | B77: 61033c9e7a297215977bdbf88dd81b3bca8073d17e7ae88f2ae7b57ce1fd58ae | C77: 3 | D77: Vol-I I ITB - Copy.docx | E77: Duplicate comparison; P13 content/XML screening

Sheet Requirements
A1: ID | B1: Requirement topic | C1: Source | D1: Requirement | E1: Owner | F1: Verification evidence | G1: Status
A2: P9-01 | B2: Bid security | C2: Corrigendum.pdf p1 | D2: Any e-BG must be executed on NeSL before the tender closing deadline; later execution is liable to rejection. | E2: Treasury / Bid Manager | F2: Record portal execution timestamp and evidence; reconcile actual closing date with all extension notices. | G2: OPEN — source requirement; execution not evidenced
A3: P9-02 | B3: Bid validity | C3: Corrigendum_2.pdf pp1-2,5; Corrigendum_4.pdf p1; CQ_replies_BRRP.pdf pp2-3 | D3: Bid security extends 45 days beyond bid validity or extended validity. Bid validity is 120 days after opening of unpriced techno-contractual bids; do not anchor it to submission closing. | E3: Treasury / Contracts | F3: Use actual opening date; diarise bid and security expiry separately. Surety claim-period provisions remain distinct. | G3: OPEN — source requirement; execution not evidenced
A4: P9-03 | B4: Performance security | C4: Corrigendum_1_BRRP.pdf p1 | D4: The quoted ITB 28.1 option for 3% initial security plus 7% progressive deductions is deleted. | E4: Contracts / Finance | F4: Remove that financing assumption; reconcile remaining ITB 28.1, IFB and B-3 for governing amounts, submission and validity. Do not infer replacement wording from deletion alone. | G4: OPEN — source requirement; execution not evidenced
A5: P9-04 | B5: Supporting-company guarantees | C5: Corrigendum_2.pdf pp2-5 | D5: B-19/B-20/B-22 specified guarantee deadlines change from 15 to 30 days from NOA. Applicable supporting/JV guarantee provisions include delayed-submission recovery wording. | E5: Contracts / Treasury | F5: Set separate applicable-route milestones. Review 1.5% of performance-security amount per month or part-month recovery wording; do not apply indiscriminately to every guarantee. | G5: OPEN — source requirement; execution not evidenced
A6: P9-05 | B6: Setting out and changes | C6: Corrigendum_3.pdf p1, GCC 2.3.6 | D6: Modified column reinstates setting-out responsibility. Contractor corrects its positioning errors; company checking does not relieve it. Later company data/instructions after pre-engineering survey causing scope changes are dealt with under Clause 8.0. | E6: Survey / Engineering / Contracts | F6: Establish controlled datums, coordinates, survey acceptance and independent dimensional checks; preserve instruction/change evidence. This clause is not deleted. | G6: OPEN — source requirement; execution not evidenced
A7: P9-06 | B7: Domestic steel compliance | C7: Corrigendum_3.pdf pp1-8 | D7: DMI&SP policy reference changes to notification dated 17 December 2025, G.S.R.904(E). All bidders submit Form-1; item-specific Melt & Pour and domestic-value-addition provisions apply. | E7: Procurement / QA / Contracts | F7: Classify items under policy Appendix A/B and HS code. Obtain heat/mill origin records, Form-1, authorisations and applicable auditor certificates; maintain traceability. Do not confuse these policy appendices with tender appendices. | G7: OPEN — source requirement; execution not evidenced
A8: P9-07 | B8: MSE and local content | C8: CQ_replies_BRRP.pdf p5 | D8: ONGC reply says PPP-MSE exemption/purchase-preference benefits do not apply to this LSTK works tender. PP-MII is referred to ITB23.6.2(b). | E8: Bid / Procurement | F8: Remove assumed MSE EMD exemption; verify PP-MII separately, including current amendments. | G8: OPEN — source requirement; execution not evidenced
A9: P9-08 | B9: Bid content | C9: CQ_replies_BRRP.pdf p6 | D9: ONGC reply requires only BRS Part V-A with Quoted/Not Quoted confirmations in the unpriced bid; price manner follows the actual price format. | E9: Bid Manager | F9: Keep prices in the correct cover; reconcile all A-3 line items and BRS. This reply does not waive separate subcontractor commitment requirements. | G9: OPEN — source requirement; execution not evidenced
A10: P9-09 | B10: Tax and precedence | C10: CQ_replies_BRRP.pdf pp7-9 | D10: Beyond-12NM works are not declared tax-exempt: prevailing GST applies; offshore GSTIN may be used. SCC overrides GCC for conflicts; complete priority is referred to B-4. Liability reduction request was rejected. | E10: Tax / Contracts | F10: Prepare transaction-specific GST, customs and withholding matrix; use B-4 for full hierarchy. Do not adopt the bidder-proposed document hierarchy or 15% liability cap. | G10: OPEN — source requirement; execution not evidenced
A11: P9-10 | B11: Pre-bid and extension requests | C11: Corrigendum_1_BRRP.pdf p1; CQ_replies_BRRP.pdf pp7,9 | D11: Pre-bid conference was physical only, 8 April 2026. Six-week bid extension request was called premature at PBC stage. | E11: Document Control / Bid | F11: Record historical event; use issued extension notices for actual deadline. This reply is not a six-week extension grant. | G11: OPEN — source requirement; execution not evidenced
A12: P9-11 | B12: Integrity pact | C12: IP (1).pdf pp2,4-6; IP.pdf identical | D12: Disclose intermediaries and relevant transgressions, obtain subcontractor adoption undertakings, retain records for IEM access. Contractor pact duration extends 12 months beyond last payment; other bidders six months after award, subject to outstanding claims. | E12: Compliance / Contracts | F12: Maintain signed pact, partner/consortium signatures as applicable, declarations and subcontract flow-down; extend compliance retention beyond physical completion. No signed compliance evidence established by blank form. | G12: OPEN — source requirement; execution not evidenced
... A103: P13-13 | B103: Unclassified file | C103: ticket.pdf; unique-content extract | D103: Classify separately based on actual content. A personal/travel document does not change project technical or commercial scope merely because uploaded with tender documents. | E103: Workstream accountable owner | F103: Exclude unrelated personal information from shared project deliverables; do not treat a ticket as project award, approval or mobilisation evidence without a relevant explicit reference. | G103: Carry-forward action; requires actual evidence

Sheet Bridge MTO
A1: Bridge | B1: Work type | C1: New bridge MT | D1: Bridge strengthen MT | E1: New landing MT | F1: Landing strengthen MT | G1: Demolition MT | H1: Handrail m | I1: Grating m2 | J1: GI sheet m2 | K1: Construction MT | L1: Status
A2: ICW-ICG UD | B2: Strengthening | C2: 0 | D2: 19 | E2: 0 | F2: 30 | G2: 25 | H2: 110 | I2: 58 | J2: 273 | K2: 49 | L2: SOURCE TRANSCRIPTION; NOT PROCUREMENT BOM
A3: ICW-ICG LD | B3: New/replacement | C3: 57 | D3: 0 | E3: 65 | F3: 0 | G3: 1 | H3: 118 | I3: 88 | J3: 0 | K3: 122 | L3: SOURCE TRANSCRIPTION; NOT PROCUREMENT BOM
A4: ICG-ICP UD | B4: Strengthening | C4: 0 | D4: 86 | E4: 0 | F4: 30 | G4: 25 | H4: 93 | I4: 49 | J4: 419 | K4: 116 | L4: SOURCE TRANSCRIPTION; NOT PROCUREMENT BOM
A5: ICG-ICP LD | B5: New/replacement | C5: 115 | D5: 0 | E5: 45 | F5: 0 | G5: 1 | H5: 176 | I5: 132 | J5: 0 | K5: 160 | L5: SOURCE TRANSCRIPTION; NOT PROCUREMENT BOM
A6: BHS-SLQ | B6: Replacement/services | C6: 195 | D6: 0 | E6: 87 | F6: 0 | G6: 210 | H6: 88 | I6: 82 | J6: 332 | K6: 282 | L6: SOURCE TRANSCRIPTION; NOT PROCUREMENT BOM
A7: SLQ-WIS | B7: Strengthening | C7: 0 | D7: 61 | E7: 0 | F7: 30 | G7: 15 | H7: 98 | I7: 51 | J7: 0 | K7: 91 | L7: SOURCE TRANSCRIPTION; NOT PROCUREMENT BOM
A8: NQO-NQD | B8: Strengthening | C8: 0 | D8: 63 | E8: 0 | F8: 30 | G8: 25 | H8: 93 | I8: 58 | J8: 250 | K8: 93 | L8: SOURCE TRANSCRIPTION; NOT PROCUREMENT BOM
A9: WIN-NC | B9: Strengthening | C9: 0 | D9: 6 | E9: 0 | F9: 40 | G9: 10 | H9: 45 | I9: 29 | J9: 0 | K9: 46 | L9: SOURCE TRANSCRIPTION; NOT PROCUREMENT BOM
A10: SCA-SC1 | B10: Strengthening | C10: 0 | D10: 35 | E10: 0 | F10: 28 | G10: 15 | H10: 88 | I10: 55 | J10: 0 | K10: 63 | L10: SOURCE TRANSCRIPTION; NOT PROCUREMENT BOM
A11: SCA-SCF | B11: Strengthening | C11: 0 | D11: 91 | E11: 0 | F11: 28 | G11: 30 | H11: 257 | I11: 116 | J11: 0 | K11: 119 | L11: SOURCE TRANSCRIPTION; NOT PROCUREMENT BOM

Sheet MTO Reconciliation
A1: Item | B1: Printed total | C1: Sum source rows | D1: Difference | E1: Action
A2: New bridge MT | B2: 367 | C2: 367 | D2: 0 | E2: Verify released design
A3: Bridge strengthen MT | B3: 361 | C3: 361 | D3: 0 | E3: Verify released design
A4: New landing MT | B4: 197 | C4: 197 | D4: 0 | E4: Verify released design
A5: Landing strengthen MT | B5: 217 | C5: 216 | D5: 1 | E5: Resolve source discrepancy
A6: Structural MT | B6: 1142 | C6: 1141 | D6: 1 | E6: Resolve before purchase baseline
A7: Demolition MT | B7: 357 | C7: 357 | D7: 0 | E7: Verify removal allocations
A8: Handrail m | B8: 1168 | C8: 1166 | D8: 2 | E8: Resolve source discrepancy
A9: Grating m2 | B9: 719 | C9: 718 | D9: 1 | E9: Resolve source discrepancy
A10: GI sheeting m2 | B10: 1274 | C10: 1274 | D10: 0 | E10: Verify design areas

Sheet Design Basis
A1: Parameter | B1: Source criterion / query | C1: Reference | D1: Required resolution
A2: Design life | B2: New bridges25years | C2: CriteriaPartII p119 | D2: Confirm remaining/new component applicability
A3: Elastic modulus | B3: 210000MPa | C3: Criteria p66 | D3: Use approved material model
A4: Density | B4: 7850kg/m3 | C4: Criteria p66 | D4: Coatings/attachments/rigging separate
A5: Global walkway live load | B5: 250kg/m2 | C5: Criteria pp42–43 | D5: Do not replace local grating criteria
A6: Local grating load | B6: 500kg/m2 | C6: Criteria p70 | D6: Apply local design/approved combinations
A7: Clear walkway | B7: At least1.2m plus services allowance | C7: Criteria pp42–43 | D7: Verify actual service envelope
A8: Piping load allowance | B8: Operating/planned future plus20% as stated | C8: Criteria pp42–43 | D8: Resolve double-counting of future services
A9: Bearing system | B9: Pinned/hinged and sliding/PTFE-equivalent with guides | C9: Criteria pp42–43 | D9: Resolve BHS fixed/sliding source conflict
A10: Movement/thrust | B10: 150% specified platform translations/thrust basis | C10: Criteria pp42–43 | D10: Use verified platform movements and reactions
A11: Deflection | B11: Vertical L/400;lateral wind L/500 | C11: Criteria p86 | D11: Verify governing span and load case
A12: Camber | B12: Compensate DL; studies and generic L/200 conflict | C12: Criteria/source bridge studies | D12: Resolve profile rather than assume L/200
... A16: Geometry reference | B16: Tender dimensions indicative; survey required | C16: Combined1 GA notes; A9 | D16: Do not adopt study span as surveyed geometry

Sheet Engineering DCI
A1: Proposed document ID | B1: Bridge/platform | C1: Deliverable | D1: Mother/input dependency | E1: Document category A/I/R | F1: Review disposition A/B/C | G1: Status | H1: Source/evidence | I1: Owner
A2: SHV-B01-DB-R0 | B2: ICW-ICG UD | C2: Bridge-specific design basis | D2: Survey and controlling criteria | E2: TBC in project DCI/MCI | F2: TBC | G2: NOT SUBMITTED | H2: No signed approval evidence | I2: Engineering
A3: SHV-B01-SUR-R0 | B3: ICW-ICG UD | C3: Pre-engineering/condition survey dossier | D3: Access, survey and NDT | E3: TBC in project DCI/MCI | F3: TBC | G3: NOT SUBMITTED | H3: No signed approval evidence | I3: Engineering
A4: SHV-B01-ANA-R0 | B4: ICW-ICG UD | C4: Global bridge/serviceability/fatigue/VIV analysis | D4: DB/SUR accepted | E4: TBC in project DCI/MCI | F4: TBC | G4: NOT SUBMITTED | H4: No signed approval evidence | I4: Engineering
A5: SHV-B01-PRE-R0 | B5: ICW-ICG UD | C5: Preservice lift/transport/temporary-stage analysis | D5: Module envelope and vessel inputs | E5: TBC in project DCI/MCI | F5: TBC | G5: NOT SUBMITTED | H5: No signed approval evidence | I5: Engineering
A6: SHV-B01-SUP-R0 | B6: ICW-ICG UD | C6: Landing/deck/support and interface reaction report | D6: Bridge/piping reactions | E6: TBC in project DCI/MCI | F6: TBC | G6: NOT SUBMITTED | H6: No signed approval evidence | I6: Engineering
A7: SHV-B01-JNT-R0 | B7: ICW-ICG UD | C7: Connection/member/bearing check report | D7: Global forces and verified materials | E7: TBC in project DCI/MCI | F7: TBC | G7: NOT SUBMITTED | H7: No signed approval evidence | I7: Engineering
A8: SHV-B01-GA-R0 | B8: ICW-ICG UD | C8: General arrangement and geometry details | D8: Accepted mother analysis | E8: TBC in project DCI/MCI | F8: TBC | G8: NOT SUBMITTED | H8: No signed approval evidence | I8: Engineering
A9: SHV-B01-SHOP-R0 | B9: ICW-ICG UD | C9: Shop member, weld, joint and erection details | D9: GA and checked connection calculations | E9: TBC in project DCI/MCI | F9: TBC | G9: NOT SUBMITTED | H9: No signed approval evidence | I9: Engineering
A10: SHV-B01-BRG-R0 | B10: ICW-ICG UD | C10: Bearing, guides, setting and restraints | D10: Movement/thrust and temperature envelope | E10: TBC in project DCI/MCI | F10: TBC | G10: NOT SUBMITTED | H10: No signed approval evidence | I10: Engineering
A11: SHV-B01-TMP-R0 | B11: ICW-ICG UD | C11: Temporary supports/stability and strengthening details | D11: Stage analyses and surveyed condition | E11: TBC in project DCI/MCI | F11: TBC | G11: NOT SUBMITTED | H11: No signed approval evidence | I11: Engineering
A12: SHV-B01-LFT-R0 | B12: ICW-ICG UD | C12: Lift/rigging/padeye/loadout procedure and drawings | D12: PRE/vessel/weight/COG | E12: TBC in project DCI/MCI | F12: TBC | G12: NOT SUBMITTED | H12: No signed approval evidence | I12: Engineering
... A184: SHV-PLAT-SCF | B184: SCF | C184: Local deck inplace assessment | D184: Verified geometry + reactions | E184: TBC | F184: TBC | G184: NOT SUBMITTED | H184: Combined1 Annexure1 p2 | I184: Structural

Sheet Tender GA Mapping
A1: Bridge | B1: Source drawing | C1: Source PDF page | D1: Use | E1: Open issue
A2: ICW–ICG LD | B2: B774-101-83-43-0001 | C2: Combined1 p27 | D2: Tender GA/source detailing | E2: RegisterRev0 vs titleRevA; survey verification
A3: ICP–ICG LD | B3: B774-102-83-43-0001 sheets1–2 | C3: Combined1 pp31–32 | D3: Tender GA/source detailing | E3: Mother calculation and survey required
A4: BHS–SLQ | B4: B774-103-83-43-0001 | C4: Combined1 p36 | D4: Tender replacement GA | E4: Bearing orientation/camber/services resolution
A5: BHS–SLQ old removal | B5: B774-103-83-43-0006 | C5: Combined1 p41 | D5: Tender removal reference | E5: Approved service transfer/temporary stability required
A6: All bridges | B6: MTO Drawings IRT and Combined1 register | C6: MTOIRT34pages; Combined1 pp3–5 | D6: Strengthening/landing/general detail sources | E6: Map34entry updated register vs older38 before omission decisions

Sheet Procurement 25
A1: Package | B1: Scope | C1: Engineering input | D1: Quantity/compliance basis | E1: Owner | F1: Price | G1: Supplier date | H1: Release gate | I1: Status
A2: STEEL-B01 | B2: ICW-ICG UD structural material | C2: B01-MTO/AFC + PS | D2: Verified member/plate BOM; grade; heat/MTC/origin | E2: Procurement | F2: UNPRICED | G2: UNCONFIRMED | H2: PS/material inspection release | I2: OPEN
A3: STEEL-B02 | B3: ICW-ICG LD structural material | C3: B02-MTO/AFC + PS | D3: Verified member/plate BOM; grade; heat/MTC/origin | E3: Procurement | F3: UNPRICED | G3: UNCONFIRMED | H3: PS/material inspection release | I3: OPEN
A4: STEEL-B03 | B4: ICG-ICP UD structural material | C4: B03-MTO/AFC + PS | D4: Verified member/plate BOM; grade; heat/MTC/origin | E4: Procurement | F4: UNPRICED | G4: UNCONFIRMED | H4: PS/material inspection release | I4: OPEN
A5: STEEL-B04 | B5: ICG-ICP LD structural material | C5: B04-MTO/AFC + PS | D5: Verified member/plate BOM; grade; heat/MTC/origin | E5: Procurement | F5: UNPRICED | G5: UNCONFIRMED | H5: PS/material inspection release | I5: OPEN
A6: STEEL-B05 | B6: BHS-SLQ structural material | C6: B05-MTO/AFC + PS | D6: Verified member/plate BOM; grade; heat/MTC/origin | E6: Procurement | F6: UNPRICED | G6: UNCONFIRMED | H6: PS/material inspection release | I6: OPEN
A7: STEEL-B06 | B7: SLQ-WIS structural material | C7: B06-MTO/AFC + PS | D7: Verified member/plate BOM; grade; heat/MTC/origin | E7: Procurement | F7: UNPRICED | G7: UNCONFIRMED | H7: PS/material inspection release | I7: OPEN
A8: STEEL-B07 | B8: NQO-NQD structural material | C8: B07-MTO/AFC + PS | D8: Verified member/plate BOM; grade; heat/MTC/origin | E8: Procurement | F8: UNPRICED | G8: UNCONFIRMED | H8: PS/material inspection release | I8: OPEN
A9: STEEL-B08 | B9: WIN-NC structural material | C9: B08-MTO/AFC + PS | D9: Verified member/plate BOM; grade; heat/MTC/origin | E9: Procurement | F9: UNPRICED | G9: UNCONFIRMED | H9: PS/material inspection release | I9: OPEN
A10: STEEL-B09 | B10: SCA-SC1 structural material | C10: B09-MTO/AFC + PS | D10: Verified member/plate BOM; grade; heat/MTC/origin | E10: Procurement | F10: UNPRICED | G10: UNCONFIRMED | H10: PS/material inspection release | I10: OPEN
A11: STEEL-B10 | B11: SCA-SCF structural material | C11: B10-MTO/AFC + PS | D11: Verified member/plate BOM; grade; heat/MTC/origin | E11: Procurement | F11: UNPRICED | G11: UNCONFIRMED | H11: PS/material inspection release | I11: OPEN
A12: BEAR | B12: Bearings, sliding interfaces and guides | C12: Applicable approved requisition/PS/service scope | D12: Quantity/specification/applicability to be confirmed | E12: Engineering | F12: UNPRICED | G12: UNCONFIRMED | H12: Applicable QA/company readiness release | I12: OPEN
... A26: TRAY | B26: Cable trays and support steel interfaces | C26: Applicable approved requisition/PS/service scope | D26: Quantity/specification/applicability to be confirmed | E26: Electrical | F26: UNPRICED | G26: UNCONFIRMED | H26: Applicable QA/company readiness release | I26: OPEN

Sheet Workpack Readiness
A1: IWP | B1: Bridge | C1: Task | D1: Unit | E1: Verified quantity | F1: Evidence index | G1: AFC | H1: Material | I1: Access PTW | J1: Crew tools | K1: ITP QA | L1: Marine SIMOPS | M1: Method | N1: Company release | O1: Readiness screen | P1: Acceptance evidence | Q1: Authorised release
A2: B01-SUR | B2: ICW-ICG UD | C2: Survey and verified access | D2: survey pack | O2: =IF(COUNTIF(G2:N2,"YES")=8,"VERIFY EVIDENCE","HOLD") | P2: Accepted geometry/NDT | Q2: NOT RELEASED
A3: B01-ENG | B3: ICW-ICG UD | C3: Design/detail/MTO release | D3: document pack | O3: =IF(COUNTIF(G3:N3,"YES")=8,"VERIFY EVIDENCE","HOLD") | P3: Checked analysis and AFC index | Q3: NOT RELEASED
A4: B01-MAT | B4: ICW-ICG UD | C4: Material and traceability receipt | D4: BOM item | O4: =IF(COUNTIF(G4:N4,"YES")=8,"VERIFY EVIDENCE","HOLD") | P4: PS/MTC/origin and TPI release | Q4: NOT RELEASED
A5: B01-FAB | B5: ICW-ICG UD | C5: Fabrication and connection work | D5: member/weld/BOM | O5: =IF(COUNTIF(G5:N5,"YES")=8,"VERIFY EVIDENCE","HOLD") | P5: WPS/welder/NDT/dimension records | Q5: NOT RELEASED
A6: B01-COAT | B6: ICW-ICG UD | C6: Preparation/coating/curing | D6: m2 by system | O6: =IF(COUNTIF(G6:N6,"YES")=8,"VERIFY EVIDENCE","HOLD") | P6: Accepted surface/environment/DFT records | Q6: NOT RELEASED
A7: B01-LOAD | B7: ICW-ICG UD | C7: Loadout/transport/receipt | D7: module | O7: =IF(COUNTIF(G7:N7,"YES")=8,"VERIFY EVIDENCE","HOLD") | P7: Weight/COG/rigging/sea-fastening approval | Q7: NOT RELEASED
A8: B01-SUP | B8: ICW-ICG UD | C8: Support strengthening and temporary stability | D8: member/joint | O8: =IF(COUNTIF(G8:N8,"YES")=8,"VERIFY EVIDENCE","HOLD") | P8: Approved stage analysis and inspected installation | Q8: NOT RELEASED
A9: B01-INST | B9: ICW-ICG UD | C9: Bridge installation/strengthening | D9: member/module | O9: =IF(COUNTIF(G9:N9,"YES")=8,"VERIFY EVIDENCE","HOLD") | P9: PTW and engineered method accepted | Q9: NOT RELEASED
A10: B01-SERV | B10: ICW-ICG UD | C10: Service transfer/testing | D10: line/circuit/system | O10: =IF(COUNTIF(G10:N10,"YES")=8,"VERIFY EVIDENCE","HOLD") | P10: Isolation/test boundary/operations acceptance | Q10: NOT RELEASED
A11: B01-DEM | B11: ICW-ICG UD | C11: Removal/scrap backload | D11: item/MT | O11: =IF(COUNTIF(G11:N11,"YES")=8,"VERIFY EVIDENCE","HOLD") | P11: Accepted support/service sequence and disposal receipt | Q11: NOT RELEASED
A12: B01-PUNCH | B12: ICW-ICG UD | C12: Inspection/punch closure | D12: punch item | O12: =IF(COUNTIF(G12:N12,"YES")=8,"VERIFY EVIDENCE","HOLD") | P12: Accepted ITR and blocking-punch closure | Q12: NOT RELEASED
A13: B01-TURN | B13: ICW-ICG UD | C13: As-built/turnover | D13: dossier | O13: =IF(COUNTIF(G13:N13,"YES")=8,"VERIFY EVIDENCE","HOLD") | P13: Accepted bridge/system completion | Q13: NOT RELEASED
... A121: B10-TURN | B121: SCA-SCF | C121: As-built/turnover | D121: dossier | O121: =IF(COUNTIF(G121:N121,"YES")=8,"VERIFY EVIDENCE","HOLD") | P121: Accepted bridge/system completion | Q121: NOT RELEASED

Sheet Resource Commitments
A1: Resource | B1: Scenario assumption | C1: Actual capacity | D1: Availability dates | E1: Evidence | F1: Owner | G1: Status
A2: Design teams | B2: Parallel ten-bridge design assumed; loading not modelled | F2: Engineering | G2: UNVERIFIED
A3: Fabrication | B3: 2capacity-one bay chains at4MT/productive bay-day | F3: Fabrication | G3: UNVERIFIED
A4: Coating | B4: 1capacity-one cell;10yard-days/package | F4: Coating | G4: UNVERIFIED
A5: NDT | B5: No finite staffing capacity modelled | F5: QA | G5: UNVERIFIED
A6: Strengthening | B6: 3capacity-one crew chains;4MT/crew-day allowance | F6: Construction | G6: UNVERIFIED
A7: Heavy lift | B7: 1capacity-one new-bridge installation chain | F7: Marine | G7: UNVERIFIED
A8: Cargo | B8: 1capacity-one transport/demob chain | F8: Logistics | G8: UNVERIFIED
A9: Services | B9: 1capacity-one transfer/test team | F9: Commissioning | G9: UNVERIFIED
A10: Removal | B10: 1capacity-one removal team | F10: Construction | G10: UNVERIFIED
A11: Survey | B11: 1spread for common field survey | F11: Survey | G11: UNVERIFIED
A12: Accommodation | B12: Minimum60special-personnel requirement; totalPOB not proven | F12: Marine | G12: UNVERIFIED

Sheet Schedule 285
A1: ID | B1: Bridge | C1: Activity | D1: Duration | E1: Calendar | F1: Predecessors | G1: Resource | H1: Owner | I1: ES | J1: EF exclusive | K1: LS | L1: LF exclusive | M1: Float calendar days | N1: Basis | O1: Status
A2: START | B2: COMMON | C2: Assumed commencement — scenario only | D2: 0 | E2: ALL | H2: Contracts | I2: 2026-11-01 | J2: 2026-11-01 | K2: 2026-11-02 | L2: 2026-11-02 | M2: 1 | N2: 1Nov2026 assumed; actual NOA unconfirmed | O2: PROPOSED / NOT APPROVED
A3: G01 | B3: COMMON | C3: Contract/amendment matrix and scope reconciliation | D3: 5 | E3: OFFICE | F3: START | H3: Contracts | I3: 2026-11-02 | J3: 2026-11-07 | K3: 2026-11-02 | L3: 2026-11-09 | M3: 0 | N3: Proposed allowance; replace with verified inputs | O3: PROPOSED / NOT APPROVED
A4: G02 | B4: COMMON | C4: Survey permits, access and mobilisation preparation | D4: 10 | E4: OFFICE | F4: G01 | H4: Survey / Operations | I4: 2026-11-09 | J4: 2026-11-21 | K4: 2026-11-09 | L4: 2026-11-22 | M4: 0 | N4: Proposed allowance; replace with verified inputs | O4: PROPOSED / NOT APPROVED
A5: G03 | B5: COMMON | C5: Pre-engineering survey campaign | D5: 15 | E5: OFF | F5: G02;D-SURV | G5: Survey spread | H5: Survey | I5: 2026-11-21 | J5: 2026-12-06 | K5: 2026-11-22 | L5: 2026-12-07 | M5: 1 | N5: Proposed allowance; replace with verified inputs | O5: PROPOSED / NOT APPROVED
A6: G04 | B6: COMMON | C6: Survey reports, geometry/condition reconciliation | D6: 5 | E6: OFFICE | F6: G03 | H6: Engineering | I6: 2026-12-07 | J6: 2026-12-12 | K6: 2026-12-07 | L6: 2026-12-14 | M6: 0 | N6: Proposed allowance; replace with verified inputs | O6: PROPOSED / NOT APPROVED
A7: G05 | B7: COMMON | C7: Survey/basis review and comment closure allowance | D7: 10 | E7: OFFICE | F7: G04 | H7: Engineering | I7: 2026-12-14 | J7: 2026-12-26 | K7: 2026-12-14 | L7: 2026-12-28 | M7: 0 | N7: Proposed allowance; replace with verified inputs | O7: PROPOSED / NOT APPROVED
A8: P-BEAR | B8: COMMON | C8: Bearings, sliding interfaces and guides — requisition/technical scope | D8: 5 | E8: OFFICE | F8: G05 | H8: Engineering | I8: 2026-12-28 | J8: 2027-01-02 | K8: 2027-11-05 | L8: 2027-11-12 | M8: 312 | N8: Proposed allowance; replace with verified inputs | O8: PROPOSED / NOT APPROVED
A9: R-BEAR | B9: COMMON | C9: Bearings, sliding interfaces and guides — bid/PS review allowance | D9: 10 | E9: OFFICE | F9: P-BEAR | H9: Engineering | I9: 2027-01-04 | J9: 2027-01-16 | K9: 2027-11-12 | L9: 2027-11-26 | M9: 312 | N9: Proposed allowance; replace with verified inputs | O9: PROPOSED / NOT APPROVED
A10: D-BEAR | B10: COMMON | C10: Bearings, sliding interfaces and guides — delivery/readiness | D10: 35 | E10: ALL | F10: R-BEAR | H10: Engineering | I10: 2027-01-16 | J10: 2027-02-20 | K10: 2027-11-26 | L10: 2027-12-31 | M10: 314 | N10: Unverified vendor/service lead-time allowance; no quote or commitment | O10: PROPOSED / NOT APPROVED
A11: P-GRAT | B11: COMMON | C11: Grating, handrail and GI sheet supply — requisition/technical scope | D11: 5 | E11: OFFICE | F11: G05 | H11: Procurement | I11: 2026-12-28 | J11: 2027-01-02 | K11: 2027-11-05 | L11: 2027-11-12 | M11: 312 | N11: Proposed allowance; replace with verified inputs | O11: PROPOSED / NOT APPROVED
A12: R-GRAT | B12: COMMON | C12: Grating, handrail and GI sheet supply — bid/PS review allowance | D12: 10 | E12: OFFICE | F12: P-GRAT | H12: Procurement | I12: 2027-01-04 | J12: 2027-01-16 | K12: 2027-11-12 | L12: 2027-11-26 | M12: 312 | N12: Proposed allowance; replace with verified inputs | O12: PROPOSED / NOT APPROVED
A13: D-GRAT | B13: COMMON | C13: Grating, handrail and GI sheet supply — delivery/readiness | D13: 35 | E13: ALL | F13: R-GRAT | H13: Procurement | I13: 2027-01-16 | J13: 2027-02-20 | K13: 2027-11-26 | L13: 2027-12-31 | M13: 314 | N13: Unverified vendor/service lead-time allowance; no quote or commitment | O13: PROPOSED / NOT APPROVED
A14: P-PIPE | B14: COMMON | C14: Piping tie-ins, fittings and supports — requisition/technical scope | D14: 5 | E14: OFFICE | F14: G05 | H14: Piping | I14: 2026-12-28 | J14: 2027-01-02 | K14: 2027-11-09 | L14: 2027-11-16 | M14: 316 | N14: Proposed allowance; replace with verified inputs | O14: PROPOSED / NOT APPROVED
A15: R-PIPE | B15: COMMON | C15: Piping tie-ins, fittings and supports — bid/PS review allowance | D15: 10 | E15: OFFICE | F15: P-PIPE | H15: Piping | I15: 2027-01-04 | J15: 2027-01-16 | K15: 2027-11-16 | L15: 2027-11-30 | M15: 316 | N15: Proposed allowance; replace with verified inputs | O15: PROPOSED / NOT APPROVED
A16: D-PIPE | B16: COMMON | C16: Piping tie-ins, fittings and supports — delivery/readiness | D16: 45 | E16: ALL | F16: R-PIPE | H16: Piping | I16: 2027-01-16 | J16: 2027-03-02 | K16: 2027-11-30 | L16: 2028-01-14 | M16: 318 | N16: Unverified vendor/service lead-time allowance; no quote or commitment | O16: PROPOSED / NOT APPROVED
A17: P-ELEC | B17: COMMON | C17: Electrical materials and bonding — requisition/technical scope | D17: 5 | E17: OFFICE | F17: G05 | H17: Electrical | I17: 2026-12-28 | J17: 2027-01-02 | K17: 2027-11-15 | L17: 2027-11-22 | M17: 322 | N17: Proposed allowance; replace with verified inputs | O17: PROPOSED / NOT APPROVED
... A63: B05-MAT | B63: BHS-SLQ | C63: Mill production, inspection and steel delivery | D63: 45 | E63: ALL | F63: B05-PO | H63: Procurement | I63: 2027-04-03 | J63: 2027-05-18 | K63: 2027-04-03 | L63: 2027-05-18 | M63: 0 | N63: Unquoted45calendar-day placeholder; origin, mill capacity and transport unresolved | O63: PROPOSED / NOT APPROVED
A64: B05-FAB | B64: BHS-SLQ | C64: Fit-up, welding and dimensional control | D64: 71 | E64: YARD | F64: B05-MAT;D-NDT;D-TPI | G64: Fabrication line 1 | H64: Fabrication | I64: 2027-05-18 | J64: 2027-08-08 | K64: 2027-05-18 | L64: 2027-08-09 | M64: 0 | N64: Assumed4MT per productive bay-day; includes aggregate steel, not validated shop productivity | O64: PROPOSED / NOT APPROVED
A65: B05-NDT | B65: BHS-SLQ | C65: NDT, repair allowance and dimensional release | D65: 6 | E65: YARD | F65: B05-FAB | H65: QA | I65: 2027-08-09 | J65: 2027-08-15 | K65: 2027-09-16 | L65: 2027-09-23 | M65: 38 | N65: Proposed allowance; replace with verified inputs | O65: PROPOSED / NOT APPROVED
A66: B05-COA | B66: BHS-SLQ | C66: Surface preparation, coating and curing allowance | D66: 10 | E66: YARD | F66: B05-NDT;D-COAT | G66: Coating cell | H66: Coating | I66: 2027-08-16 | J66: 2027-08-27 | K66: 2027-09-23 | L66: 2027-10-05 | M66: 38 | N66: Proposed allowance; replace with verified inputs | O66: PROPOSED / NOT APPROVED
A67: B05-REL | B67: BHS-SLQ | C67: Trial fit, verified weight/COG and loadout release | D67: 5 | E67: YARD | F67: B05-COA | H67: QA / Marine | I67: 2027-08-27 | J67: 2027-09-02 | K67: 2027-11-19 | L67: 2027-11-25 | M67: 84 | N67: Proposed allowance; replace with verified inputs | O67: PROPOSED / NOT APPROVED
A68: B05-TRN | B68: BHS-SLQ | C68: Loadout, transport and offshore receipt | D68: 3 | E68: OFF | F68: B05-REL;D-CARGO | G68: Cargo spread | H68: Logistics | I68: 2027-10-16 | J68: 2027-10-19 | K68: 2027-11-25 | L68: 2027-11-28 | M68: 40 | N68: Proposed allowance; replace with verified inputs | O68: PROPOSED / NOT APPROVED
A69: B05-PRE | B69: BHS-SLQ | C69: PTW, access, SIMOPS and work-front readiness | D69: 3 | E69: OFF | F69: B05-TRN;D-SCAF;D-PPE | H69: Construction | I69: 2027-10-19 | J69: 2027-10-22 | K69: 2027-11-28 | L69: 2027-12-01 | M69: 40 | N69: Proposed allowance; replace with verified inputs | O69: PROPOSED / NOT APPROVED
A70: B05-STR | B70: BHS-SLQ | C70: Landing/platform pre-install strengthening | D70: 22 | E70: OFF | F70: B05-PRE | G70: Strength crew 1 | H70: Construction | I70: 2027-10-22 | J70: 2027-11-13 | K70: 2027-12-01 | L70: 2027-12-23 | M70: 40 | N70: Proposed4MT/crew-day; actual weld/access quantities not validated | O70: PROPOSED / NOT APPROVED
A71: B05-INS | B71: BHS-SLQ | C71: New bridge installation | D71: 7 | E71: OFF | F71: B05-STR;D-MAR;D-BEAR;D-GRAT | G71: Heavy-lift spread | H71: Marine / Construction | I71: 2027-11-13 | J71: 2027-11-20 | K71: 2028-01-03 | L71: 2028-01-10 | M71: 51 | N71: Aggregate planning allowance; engineered lifts and temporary stability required | O71: PROPOSED / NOT APPROVED
A72: B05-SRV | B72: BHS-SLQ | C72: Services transfer, test and accepted reinstatement | D72: 5 | E72: OFF | F72: B05-INS;D-PIPE;D-ELEC;D-INST;D-TRAY | G72: Service transfer team | H72: Commissioning | I72: 2027-11-20 | J72: 2027-11-25 | K72: 2028-01-14 | L72: 2028-01-19 | M72: 55 | N72: Proposed allowance; replace with verified inputs | O72: PROPOSED / NOT APPROVED
A73: B05-DEM | B73: BHS-SLQ | C73: Engineered demolition/removal and scrap backload | D73: 14 | E73: OFF | F73: B05-SRV | G73: Removal team | H73: Construction | I73: 2027-11-25 | J73: 2027-12-09 | K73: 2028-02-03 | L73: 2028-02-17 | M73: 70 | N73: Proposed15MT/day allowance; BHS sequence after safe new service transfer, subject to approved method | O73: PROPOSED / NOT APPROVED
A74: B05-PUN | B74: BHS-SLQ | C74: Inspection, touch-up and offshore punch closure | D74: 3 | E74: OFF | F74: B05-DEM | H74: QA / Commissioning | I74: 2027-12-09 | J74: 2027-12-12 | K74: 2028-03-06 | L74: 2028-03-09 | M74: 88 | N74: Proposed allowance; replace with verified inputs | O74: PROPOSED / NOT APPROVED
A75: B05-DOS | B75: BHS-SLQ | C75: As-built, QA and turnover dossier acceptance | D75: 10 | E75: OFFICE | F75: B05-PUN | H75: Document Control | I75: 2027-12-13 | J75: 2027-12-25 | K75: 2028-03-09 | L75: 2028-03-23 | M75: 87 | N75: Proposed allowance; replace with verified inputs | O75: PROPOSED / NOT APPROVED
A76: B02-BAS | B76: ICW-ICG LD | C76: Design basis, loads and interfaces | D76: 5 | E76: OFFICE | F76: G05;D-DES | H76: Engineering | I76: 2026-12-28 | J76: 2027-01-02 | K76: 2027-04-02 | L76: 2027-04-09 | M76: 95 | N76: Proposed allowance; replace with verified inputs | O76: PROPOSED / NOT APPROVED
A77: B02-BRV | B77: ICW-ICG LD | C77: Basis review and comment closure allowance | D77: 10 | E77: OFFICE | F77: B02-BAS | H77: Engineering | I77: 2027-01-04 | J77: 2027-01-16 | K77: 2027-04-09 | L77: 2027-04-23 | M77: 95 | N77: Proposed allowance; replace with verified inputs | O77: PROPOSED / NOT APPROVED
A78: B02-ANA | B78: ICW-ICG LD | C78: Bridge/platform and preservice analysis preparation | D78: 20 | E78: OFFICE | F78: B02-BRV | H78: Structural | I78: 2027-01-18 | J78: 2027-02-13 | K78: 2027-04-23 | L78: 2027-05-21 | M78: 95 | N78: Proposed engineering effort window; native analysis/check evidence not supplied | O78: PROPOSED / NOT APPROVED
A79: B02-ARV | B79: ICW-ICG LD | C79: Analysis review and comment closure allowance | D79: 10 | E79: OFFICE | F79: B02-ANA | H79: Engineering | I79: 2027-02-15 | J79: 2027-02-27 | K79: 2027-05-21 | L79: 2027-06-04 | M79: 95 | N79: Proposed allowance; replace with verified inputs | O79: PROPOSED / NOT APPROVED
A80: B02-DET | B80: ICW-ICG LD | C80: Connection, bearing, landing and workpack detailing | D80: 15 | E80: OFFICE | F80: B02-ARV | H80: Structural | I80: 2027-03-01 | J80: 2027-03-20 | K80: 2027-06-04 | L80: 2027-06-25 | M80: 95 | N80: Proposed allowance; replace with verified inputs | O80: PROPOSED / NOT APPROVED
A81: B02-DRV | B81: ICW-ICG LD | C81: Drawing review and comment closure allowance | D81: 10 | E81: OFFICE | F81: B02-DET | H81: Engineering | I81: 2027-03-22 | J81: 2027-04-03 | K81: 2027-06-25 | L81: 2027-07-09 | M81: 95 | N81: Proposed allowance; replace with verified inputs | O81: PROPOSED / NOT APPROVED
A82: B02-AFC | B82: ICW-ICG LD | C82: AFC design/MTO independent check and release gate | D82: 0 | E82: ALL | F82: B02-DRV | H82: Engineering | I82: 2027-04-03 | J82: 2027-04-03 | K82: 2027-07-09 | L82: 2027-07-09 | M82: 97 | N82: Gate; actual signed release not established | O82: PROPOSED / NOT APPROVED
A83: B02-RFQ | B83: ICW-ICG LD | C83: Bridge steel RFQ, evaluation and PS preparation | D83: 7 | E83: OFFICE | F83: B02-BRV | H83: Procurement | I83: 2027-01-18 | J83: 2027-01-27 | K83: 2027-06-16 | L83: 2027-06-25 | M83: 149 | N83: Proposed allowance; replace with verified inputs | O83: PROPOSED / NOT APPROVED
A84: B02-PRV | B84: ICW-ICG LD | C84: Bridge steel PS review allowance | D84: 10 | E84: OFFICE | F84: B02-RFQ | H84: Procurement | I84: 2027-01-27 | J84: 2027-02-10 | K84: 2027-06-25 | L84: 2027-07-09 | M84: 149 | N84: Proposed allowance; replace with verified inputs | O84: PROPOSED / NOT APPROVED
A85: B02-PO | B85: ICW-ICG LD | C85: Bridge steel compliant PO release gate | D85: 0 | E85: ALL | F85: B02-AFC;B02-PRV | H85: Procurement | I85: 2027-04-03 | J85: 2027-04-03 | K85: 2027-07-09 | L85: 2027-07-09 | M85: 97 | N85: No at-risk purchase assumed; amended domestic-origin evidence required | O85: PROPOSED / NOT APPROVED
A86: B02-MAT | B86: ICW-ICG LD | C86: Mill production, inspection and steel delivery | D86: 45 | E86: ALL | F86: B02-PO | H86: Procurement | I86: 2027-04-03 | J86: 2027-05-18 | K86: 2027-07-09 | L86: 2027-08-23 | M86: 97 | N86: Unquoted45calendar-day placeholder; origin, mill capacity and transport unresolved | O86: PROPOSED / NOT APPROVED
A87: B02-FAB | B87: ICW-ICG LD | C87: Fit-up, welding and dimensional control | D87: 31 | E87: YARD | F87: B02-MAT;D-NDT;D-TPI | G87: Fabrication line 2 | H87: Fabrication | I87: 2027-05-18 | J87: 2027-06-23 | K87: 2027-08-23 | L87: 2027-09-28 | M87: 97 | N87: Assumed4MT per productive bay-day; includes aggregate steel, not validated shop productivity | O87: PROPOSED / NOT APPROVED
A88: B02-NDT | B88: ICW-ICG LD | C88: NDT, repair allowance and dimensional release | D88: 6 | E88: YARD | F88: B02-FAB | H88: QA | I88: 2027-06-23 | J88: 2027-06-30 | K88: 2027-09-28 | L88: 2027-10-05 | M88: 97 | N88: Proposed allowance; replace with verified inputs | O88: PROPOSED / NOT APPROVED
A89: B02-COA | B89: ICW-ICG LD | C89: Surface preparation, coating and curing allowance | D89: 10 | E89: YARD | F89: B02-NDT;D-COAT;B05-COA | G89: Coating cell | H89: Coating | I89: 2027-08-27 | J89: 2027-09-08 | K89: 2027-10-05 | L89: 2027-10-16 | M89: 39 | N89: Proposed allowance; replace with verified inputs | O89: PROPOSED / NOT APPROVED
A90: B02-REL | B90: ICW-ICG LD | C90: Trial fit, verified weight/COG and loadout release | D90: 5 | E90: YARD | F90: B02-COA | H90: QA / Marine | I90: 2027-09-08 | J90: 2027-09-14 | K90: 2027-12-06 | L90: 2027-12-11 | M90: 89 | N90: Proposed allowance; replace with verified inputs | O90: PROPOSED / NOT APPROVED
A91: B02-TRN | B91: ICW-ICG LD | C91: Loadout, transport and offshore receipt | D91: 3 | E91: OFF | F91: B02-REL;D-CARGO;B05-TRN | G91: Cargo spread | H91: Logistics | I91: 2027-10-19 | J91: 2027-10-22 | K91: 2027-12-11 | L91: 2027-12-14 | M91: 53 | N91: Proposed allowance; replace with verified inputs | O91: PROPOSED / NOT APPROVED
A92: B02-PRE | B92: ICW-ICG LD | C92: PTW, access, SIMOPS and work-front readiness | D92: 3 | E92: OFF | F92: B02-TRN;D-SCAF;D-PPE | H92: Construction | I92: 2027-10-22 | J92: 2027-10-25 | K92: 2027-12-15 | L92: 2027-12-18 | M92: 54 | N92: Proposed allowance; replace with verified inputs | O92: PROPOSED / NOT APPROVED
A93: B02-STR | B93: ICW-ICG LD | C93: Landing/platform pre-install strengthening | D93: 17 | E93: OFF | F93: B02-PRE | G93: Strength crew 2 | H93: Construction | I93: 2027-10-25 | J93: 2027-11-11 | K93: 2027-12-18 | L93: 2028-01-04 | M93: 54 | N93: Proposed4MT/crew-day; actual weld/access quantities not validated | O93: PROPOSED / NOT APPROVED
A94: B02-INS | B94: ICW-ICG LD | C94: New bridge installation | D94: 7 | E94: OFF | F94: B02-STR;D-MAR;D-BEAR;D-GRAT;B05-INS | G94: Heavy-lift spread | H94: Marine / Construction | I94: 2027-11-20 | J94: 2027-11-27 | K94: 2028-01-10 | L94: 2028-01-17 | M94: 51 | N94: Aggregate planning allowance; engineered lifts and temporary stability required | O94: PROPOSED / NOT APPROVED
A95: B02-SRV | B95: ICW-ICG LD | C95: Services transfer, test and accepted reinstatement | D95: 5 | E95: OFF | F95: B02-INS;D-PIPE;D-ELEC;D-INST;D-TRAY;B05-SRV | G95: Service transfer team | H95: Commissioning | I95: 2027-11-27 | J95: 2027-12-02 | K95: 2028-01-19 | L95: 2028-01-24 | M95: 53 | N95: Proposed allowance; replace with verified inputs | O95: PROPOSED / NOT APPROVED
A96: B02-DEM | B96: ICW-ICG LD | C96: Engineered demolition/removal and scrap backload | D96: 2 | E96: OFF | F96: B02-SRV;B05-DEM | G96: Removal team | H96: Construction | I96: 2027-12-09 | J96: 2027-12-11 | K96: 2028-02-17 | L96: 2028-02-19 | M96: 70 | N96: Proposed15MT/day allowance; BHS sequence after safe new service transfer, subject to approved method | O96: PROPOSED / NOT APPROVED
A97: B02-PUN | B97: ICW-ICG LD | C97: Inspection, touch-up and offshore punch closure | D97: 3 | E97: OFF | F97: B02-DEM | H97: QA / Commissioning | I97: 2027-12-11 | J97: 2027-12-14 | K97: 2028-03-06 | L97: 2028-03-09 | M97: 86 | N97: Proposed allowance; replace with verified inputs | O97: PROPOSED / NOT APPROVED
A98: B02-DOS | B98: ICW-ICG LD | C98: As-built, QA and turnover dossier acceptance | D98: 10 | E98: OFFICE | F98: B02-PUN | H98: Document Control | I98: 2027-12-14 | J98: 2027-12-28 | K98: 2028-03-09 | L98: 2028-03-23 | M98: 86 | N98: Proposed allowance; replace with verified inputs | O98: PROPOSED / NOT APPROVED
A99: B04-BAS | B99: ICG-ICP LD | C99: Design basis, loads and interfaces | D99: 5 | E99: OFFICE | F99: G05;D-DES | H99: Engineering | I99: 2026-12-28 | J99: 2027-01-02 | K99: 2027-03-19 | L99: 2027-03-26 | M99: 81 | N99: Proposed allowance; replace with verified inputs | O99: PROPOSED / NOT APPROVED
A100: B04-BRV | B100: ICG-ICP LD | C100: Basis review and comment closure allowance | D100: 10 | E100: OFFICE | F100: B04-BAS | H100: Engineering | I100: 2027-01-04 | J100: 2027-01-16 | K100: 2027-03-26 | L100: 2027-04-09 | M100: 81 | N100: Proposed allowance; replace with verified inputs | O100: PROPOSED / NOT APPROVED
A101: B04-ANA | B101: ICG-ICP LD | C101: Bridge/platform and preservice analysis preparation | D101: 20 | E101: OFFICE | F101: B04-BRV | H101: Structural | I101: 2027-01-18 | J101: 2027-02-13 | K101: 2027-04-09 | L101: 2027-05-07 | M101: 81 | N101: Proposed engineering effort window; native analysis/check evidence not supplied | O101: PROPOSED / NOT APPROVED
A102: B04-ARV | B102: ICG-ICP LD | C102: Analysis review and comment closure allowance | D102: 10 | E102: OFFICE | F102: B04-ANA | H102: Engineering | I102: 2027-02-15 | J102: 2027-02-27 | K102: 2027-05-07 | L102: 2027-05-21 | M102: 81 | N102: Proposed allowance; replace with verified inputs | O102: PROPOSED / NOT APPROVED
A103: B04-DET | B103: ICG-ICP LD | C103: Connection, bearing, landing and workpack detailing | D103: 15 | E103: OFFICE | F103: B04-ARV | H103: Structural | I103: 2027-03-01 | J103: 2027-03-20 | K103: 2027-05-21 | L103: 2027-06-11 | M103: 81 | N103: Proposed allowance; replace with verified inputs | O103: PROPOSED / NOT APPROVED
A104: B04-DRV | B104: ICG-ICP LD | C104: Drawing review and comment closure allowance | D104: 10 | E104: OFFICE | F104: B04-DET | H104: Engineering | I104: 2027-03-22 | J104: 2027-04-03 | K104: 2027-06-11 | L104: 2027-06-25 | M104: 81 | N104: Proposed allowance; replace with verified inputs | O104: PROPOSED / NOT APPROVED
A105: B04-AFC | B105: ICG-ICP LD | C105: AFC design/MTO independent check and release gate | D105: 0 | E105: ALL | F105: B04-DRV | H105: Engineering | I105: 2027-04-03 | J105: 2027-04-03 | K105: 2027-06-25 | L105: 2027-06-25 | M105: 83 | N105: Gate; actual signed release not established | O105: PROPOSED / NOT APPROVED
A106: B04-RFQ | B106: ICG-ICP LD | C106: Bridge steel RFQ, evaluation and PS preparation | D106: 7 | E106: OFFICE | F106: B04-BRV | H106: Procurement | I106: 2027-01-18 | J106: 2027-01-27 | K106: 2027-06-02 | L106: 2027-06-11 | M106: 135 | N106: Proposed allowance; replace with verified inputs | O106: PROPOSED / NOT APPROVED
A107: B04-PRV | B107: ICG-ICP LD | C107: Bridge steel PS review allowance | D107: 10 | E107: OFFICE | F107: B04-RFQ | H107: Procurement | I107: 2027-01-27 | J107: 2027-02-10 | K107: 2027-06-11 | L107: 2027-06-25 | M107: 135 | N107: Proposed allowance; replace with verified inputs | O107: PROPOSED / NOT APPROVED
A108: B04-PO | B108: ICG-ICP LD | C108: Bridge steel compliant PO release gate | D108: 0 | E108: ALL | F108: B04-AFC;B04-PRV | H108: Procurement | I108: 2027-04-03 | J108: 2027-04-03 | K108: 2027-06-25 | L108: 2027-06-25 | M108: 83 | N108: No at-risk purchase assumed; amended domestic-origin evidence required | O108: PROPOSED / NOT APPROVED
A109: B04-MAT | B109: ICG-ICP LD | C109: Mill production, inspection and steel delivery | D109: 45 | E109: ALL | F109: B04-PO | H109: Procurement | I109: 2027-04-03 | J109: 2027-05-18 | K109: 2027-06-25 | L109: 2027-08-09 | M109: 83 | N109: Unquoted45calendar-day placeholder; origin, mill capacity and transport unresolved | O109: PROPOSED / NOT APPROVED
A110: B04-FAB | B110: ICG-ICP LD | C110: Fit-up, welding and dimensional control | D110: 40 | E110: YARD | F110: B04-MAT;D-NDT;D-TPI;B05-FAB | G110: Fabrication line 1 | H110: Fabrication | I110: 2027-08-09 | J110: 2027-09-24 | K110: 2027-08-09 | L110: 2027-09-24 | M110: 0 | N110: Assumed4MT per productive bay-day; includes aggregate steel, not validated shop productivity | O110: PROPOSED / NOT APPROVED
A111: B04-NDT | B111: ICG-ICP LD | C111: NDT, repair allowance and dimensional release | D111: 6 | E111: YARD | F111: B04-FAB | H111: QA | I111: 2027-09-24 | J111: 2027-10-01 | K111: 2027-10-09 | L111: 2027-10-16 | M111: 15 | N111: Proposed allowance; replace with verified inputs | O111: PROPOSED / NOT APPROVED
A112: B04-COA | B112: ICG-ICP LD | C112: Surface preparation, coating and curing allowance | D112: 10 | E112: YARD | F112: B04-NDT;D-COAT;B02-COA | G112: Coating cell | H112: Coating | I112: 2027-10-01 | J112: 2027-10-13 | K112: 2027-10-16 | L112: 2027-10-28 | M112: 15 | N112: Proposed allowance; replace with verified inputs | O112: PROPOSED / NOT APPROVED
A113: B04-REL | B113: ICG-ICP LD | C113: Trial fit, verified weight/COG and loadout release | D113: 5 | E113: YARD | F113: B04-COA | H113: QA / Marine | I113: 2027-10-13 | J113: 2027-10-19 | K113: 2027-12-08 | L113: 2027-12-14 | M113: 56 | N113: Proposed allowance; replace with verified inputs | O113: PROPOSED / NOT APPROVED
A114: B04-TRN | B114: ICG-ICP LD | C114: Loadout, transport and offshore receipt | D114: 3 | E114: OFF | F114: B04-REL;D-CARGO;B02-TRN | G114: Cargo spread | H114: Logistics | I114: 2027-10-22 | J114: 2027-10-25 | K114: 2027-12-14 | L114: 2027-12-17 | M114: 53 | N114: Proposed allowance; replace with verified inputs | O114: PROPOSED / NOT APPROVED
A115: B04-PRE | B115: ICG-ICP LD | C115: PTW, access, SIMOPS and work-front readiness | D115: 3 | E115: OFF | F115: B04-TRN;D-SCAF;D-PPE | H115: Construction | I115: 2027-10-25 | J115: 2027-10-28 | K115: 2027-12-30 | L115: 2028-01-02 | M115: 66 | N115: Proposed allowance; replace with verified inputs | O115: PROPOSED / NOT APPROVED
A116: B04-STR | B116: ICG-ICP LD | C116: Landing/platform pre-install strengthening | D116: 12 | E116: OFF | F116: B04-PRE | G116: Strength crew 3 | H116: Construction | I116: 2027-10-28 | J116: 2027-11-09 | K116: 2028-01-02 | L116: 2028-01-14 | M116: 66 | N116: Proposed4MT/crew-day; actual weld/access quantities not validated | O116: PROPOSED / NOT APPROVED
A117: B04-INS | B117: ICG-ICP LD | C117: New bridge installation | D117: 7 | E117: OFF | F117: B04-STR;D-MAR;D-BEAR;D-GRAT;B02-INS | G117: Heavy-lift spread | H117: Marine / Construction | I117: 2027-11-27 | J117: 2027-12-04 | K117: 2028-01-17 | L117: 2028-01-24 | M117: 51 | N117: Aggregate planning allowance; engineered lifts and temporary stability required | O117: PROPOSED / NOT APPROVED
A118: B04-SRV | B118: ICG-ICP LD | C118: Services transfer, test and accepted reinstatement | D118: 5 | E118: OFF | F118: B04-INS;D-PIPE;D-ELEC;D-INST;D-TRAY;B02-SRV | G118: Service transfer team | H118: Commissioning | I118: 2027-12-04 | J118: 2027-12-09 | K118: 2028-01-24 | L118: 2028-01-29 | M118: 51 | N118: Proposed allowance; replace with verified inputs | O118: PROPOSED / NOT APPROVED
A119: B04-DEM | B119: ICG-ICP LD | C119: Engineered demolition/removal and scrap backload | D119: 2 | E119: OFF | F119: B04-SRV;B02-DEM | G119: Removal team | H119: Construction | I119: 2027-12-11 | J119: 2027-12-13 | K119: 2028-02-19 | L119: 2028-02-21 | M119: 70 | N119: Proposed15MT/day allowance; BHS sequence after safe new service transfer, subject to approved method | O119: PROPOSED / NOT APPROVED
A120: B04-PUN | B120: ICG-ICP LD | C120: Inspection, touch-up and offshore punch closure | D120: 3 | E120: OFF | F120: B04-DEM | H120: QA / Commissioning | I120: 2027-12-13 | J120: 2027-12-16 | K120: 2028-03-06 | L120: 2028-03-09 | M120: 84 | N120: Proposed allowance; replace with verified inputs | O120: PROPOSED / NOT APPROVED
A121: B04-DOS | B121: ICG-ICP LD | C121: As-built, QA and turnover dossier acceptance | D121: 10 | E121: OFFICE | F121: B04-PUN | H121: Document Control | I121: 2027-12-16 | J121: 2027-12-30 | K121: 2028-03-09 | L121: 2028-03-23 | M121: 84 | N121: Proposed allowance; replace with verified inputs | O121: PROPOSED / NOT APPROVED
A122: B01-BAS | B122: ICW-ICG UD | C122: Design basis, loads and interfaces | D122: 5 | E122: OFFICE | F122: G05;D-DES | H122: Engineering | I122: 2026-12-28 | J122: 2027-01-02 | K122: 2027-05-27 | L122: 2027-06-03 | M122: 150 | N122: Proposed allowance; replace with verified inputs | O122: PROPOSED / NOT APPROVED
A123: B01-BRV | B123: ICW-ICG UD | C123: Basis review and comment closure allowance | D123: 10 | E123: OFFICE | F123: B01-BAS | H123: Engineering | I123: 2027-01-04 | J123: 2027-01-16 | K123: 2027-06-03 | L123: 2027-06-17 | M123: 150 | N123: Proposed allowance; replace with verified inputs | O123: PROPOSED / NOT APPROVED
A124: B01-ANA | B124: ICW-ICG UD | C124: Bridge/platform and preservice analysis preparation | D124: 12 | E124: OFFICE | F124: B01-BRV | H124: Structural | I124: 2027-01-18 | J124: 2027-02-03 | K124: 2027-06-17 | L124: 2027-07-05 | M124: 150 | N124: Proposed engineering effort window; native analysis/check evidence not supplied | O124: PROPOSED / NOT APPROVED
A125: B01-ARV | B125: ICW-ICG UD | C125: Analysis review and comment closure allowance | D125: 10 | E125: OFFICE | F125: B01-ANA | H125: Engineering | I125: 2027-02-03 | J125: 2027-02-17 | K125: 2027-07-05 | L125: 2027-07-19 | M125: 152 | N125: Proposed allowance; replace with verified inputs | O125: PROPOSED / NOT APPROVED
A126: B01-DET | B126: ICW-ICG UD | C126: Connection, bearing, landing and workpack detailing | D126: 10 | E126: OFFICE | F126: B01-ARV | H126: Structural | I126: 2027-02-17 | J126: 2027-03-03 | K126: 2027-07-19 | L126: 2027-08-02 | M126: 152 | N126: Proposed allowance; replace with verified inputs | O126: PROPOSED / NOT APPROVED
A127: B01-DRV | B127: ICW-ICG UD | C127: Drawing review and comment closure allowance | D127: 10 | E127: OFFICE | F127: B01-DET | H127: Engineering | I127: 2027-03-03 | J127: 2027-03-17 | K127: 2027-08-02 | L127: 2027-08-16 | M127: 152 | N127: Proposed allowance; replace with verified inputs | O127: PROPOSED / NOT APPROVED
A128: B01-AFC | B128: ICW-ICG UD | C128: AFC design/MTO independent check and release gate | D128: 0 | E128: ALL | F128: B01-DRV | H128: Engineering | I128: 2027-03-17 | J128: 2027-03-17 | K128: 2027-08-16 | L128: 2027-08-16 | M128: 152 | N128: Gate; actual signed release not established | O128: PROPOSED / NOT APPROVED
A129: B01-RFQ | B129: ICW-ICG UD | C129: Bridge steel RFQ, evaluation and PS preparation | D129: 7 | E129: OFFICE | F129: B01-BRV | H129: Procurement | I129: 2027-01-18 | J129: 2027-01-27 | K129: 2027-07-22 | L129: 2027-08-02 | M129: 185 | N129: Proposed allowance; replace with verified inputs | O129: PROPOSED / NOT APPROVED
A130: B01-PRV | B130: ICW-ICG UD | C130: Bridge steel PS review allowance | D130: 10 | E130: OFFICE | F130: B01-RFQ | H130: Procurement | I130: 2027-01-27 | J130: 2027-02-10 | K130: 2027-08-02 | L130: 2027-08-16 | M130: 187 | N130: Proposed allowance; replace with verified inputs | O130: PROPOSED / NOT APPROVED
A131: B01-PO | B131: ICW-ICG UD | C131: Bridge steel compliant PO release gate | D131: 0 | E131: ALL | F131: B01-AFC;B01-PRV | H131: Procurement | I131: 2027-03-17 | J131: 2027-03-17 | K131: 2027-08-16 | L131: 2027-08-16 | M131: 152 | N131: No at-risk purchase assumed; amended domestic-origin evidence required | O131: PROPOSED / NOT APPROVED
A132: B01-MAT | B132: ICW-ICG UD | C132: Mill production, inspection and steel delivery | D132: 45 | E132: ALL | F132: B01-PO | H132: Procurement | I132: 2027-03-17 | J132: 2027-05-01 | K132: 2027-08-16 | L132: 2027-09-30 | M132: 152 | N132: Unquoted45calendar-day placeholder; origin, mill capacity and transport unresolved | O132: PROPOSED / NOT APPROVED
A133: B01-FAB | B133: ICW-ICG UD | C133: Fit-up, welding and dimensional control | D133: 13 | E133: YARD | F133: B01-MAT;D-NDT;D-TPI;B02-FAB | G133: Fabrication line 2 | H133: Fabrication | I133: 2027-06-23 | J133: 2027-07-08 | K133: 2027-09-30 | L133: 2027-10-15 | M133: 99 | N133: Assumed4MT per productive bay-day; includes aggregate steel, not validated shop productivity | O133: PROPOSED / NOT APPROVED
A134: B01-NDT | B134: ICW-ICG UD | C134: NDT, repair allowance and dimensional release | D134: 6 | E134: YARD | F134: B01-FAB | H134: QA | I134: 2027-07-08 | J134: 2027-07-15 | K134: 2027-10-21 | L134: 2027-10-28 | M134: 105 | N134: Proposed allowance; replace with verified inputs | O134: PROPOSED / NOT APPROVED
A135: B01-COA | B135: ICW-ICG UD | C135: Surface preparation, coating and curing allowance | D135: 10 | E135: YARD | F135: B01-NDT;D-COAT;B04-COA | G135: Coating cell | H135: Coating | I135: 2027-10-13 | J135: 2027-10-24 | K135: 2027-10-28 | L135: 2027-11-09 | M135: 15 | N135: Proposed allowance; replace with verified inputs | O135: PROPOSED / NOT APPROVED
A136: B01-REL | B136: ICW-ICG UD | C136: Trial fit, verified weight/COG and loadout release | D136: 5 | E136: YARD | F136: B01-COA | H136: QA / Marine | I136: 2027-10-25 | J136: 2027-10-30 | K136: 2027-12-11 | L136: 2027-12-17 | M136: 47 | N136: Proposed allowance; replace with verified inputs | O136: PROPOSED / NOT APPROVED
A137: B01-TRN | B137: ICW-ICG UD | C137: Loadout, transport and offshore receipt | D137: 3 | E137: OFF | F137: B01-REL;D-CARGO;B04-TRN | G137: Cargo spread | H137: Logistics | I137: 2027-10-30 | J137: 2027-11-02 | K137: 2027-12-17 | L137: 2027-12-20 | M137: 48 | N137: Proposed allowance; replace with verified inputs | O137: PROPOSED / NOT APPROVED
A138: B01-PRE | B138: ICW-ICG UD | C138: PTW, access, SIMOPS and work-front readiness | D138: 3 | E138: OFF | F138: B01-TRN;D-SCAF;D-PPE | H138: Construction | I138: 2027-11-02 | J138: 2027-11-05 | K138: 2027-12-20 | L138: 2027-12-23 | M138: 48 | N138: Proposed allowance; replace with verified inputs | O138: PROPOSED / NOT APPROVED
A139: B01-STR | B139: ICW-ICG UD | C139: Landing/platform pre-install strengthening | D139: 8 | E139: OFF | F139: B01-PRE;B05-STR | G139: Strength crew 1 | H139: Construction | I139: 2027-11-13 | J139: 2027-11-21 | K139: 2027-12-23 | L139: 2027-12-31 | M139: 40 | N139: Proposed4MT/crew-day; actual weld/access quantities not validated | O139: PROPOSED / NOT APPROVED
A140: B01-INS | B140: ICW-ICG UD | C140: Bridge strengthening and replacement items | D140: 5 | E140: OFF | F140: B01-STR;D-MAR;D-BEAR;D-GRAT | G140: Strength crew 1 | H140: Marine / Construction | I140: 2027-11-21 | J140: 2027-11-26 | K140: 2027-12-31 | L140: 2028-01-05 | M140: 40 | N140: Aggregate planning allowance; engineered lifts and temporary stability required | O140: PROPOSED / NOT APPROVED
A141: B01-SRV | B141: ICW-ICG UD | C141: Services transfer, test and accepted reinstatement | D141: 5 | E141: OFF | F141: B01-INS;D-PIPE;D-ELEC;D-INST;D-TRAY;B04-SRV | G141: Service transfer team | H141: Commissioning | I141: 2027-12-09 | J141: 2027-12-14 | K141: 2028-01-29 | L141: 2028-02-03 | M141: 51 | N141: Proposed allowance; replace with verified inputs | O141: PROPOSED / NOT APPROVED
A142: B01-DEM | B142: ICW-ICG UD | C142: Engineered demolition/removal and scrap backload | D142: 2 | E142: OFF | F142: B01-SRV;B04-DEM | G142: Removal team | H142: Construction | I142: 2027-12-14 | J142: 2027-12-16 | K142: 2028-02-21 | L142: 2028-02-23 | M142: 69 | N142: Proposed15MT/day allowance; BHS sequence after safe new service transfer, subject to approved method | O142: PROPOSED / NOT APPROVED
A143: B01-PUN | B143: ICW-ICG UD | C143: Inspection, touch-up and offshore punch closure | D143: 3 | E143: OFF | F143: B01-DEM | H143: QA / Commissioning | I143: 2027-12-16 | J143: 2027-12-19 | K143: 2028-03-06 | L143: 2028-03-09 | M143: 81 | N143: Proposed allowance; replace with verified inputs | O143: PROPOSED / NOT APPROVED
A144: B01-DOS | B144: ICW-ICG UD | C144: As-built, QA and turnover dossier acceptance | D144: 10 | E144: OFFICE | F144: B01-PUN | H144: Document Control | I144: 2027-12-20 | J144: 2028-01-01 | K144: 2028-03-09 | L144: 2028-03-23 | M144: 80 | N144: Proposed allowance; replace with verified inputs | O144: PROPOSED / NOT APPROVED
A145: B03-BAS | B145: ICG-ICP UD | C145: Design basis, loads and interfaces | D145: 5 | E145: OFFICE | F145: G05;D-DES | H145: Engineering | I145: 2026-12-28 | J145: 2027-01-02 | K145: 2027-05-21 | L145: 2027-05-28 | M145: 144 | N145: Proposed allowance; replace with verified inputs | O145: PROPOSED / NOT APPROVED
...

Sheet Driving Chain
A1: Sequence | B1: ID | C1: Activity | D1: Start | E1: Finish exclusive | F1: Float
A2: 1 | B2: START | C2: Assumed commencement — scenario only | D2: 2026-11-01 | E2: 2026-11-01 | F2: 1
A3: 2 | B3: G01 | C3: Contract/amendment matrix and scope reconciliation | D3: 2026-11-02 | E3: 2026-11-07 | F3: 0
A4: 3 | B4: G02 | C4: Survey permits, access and mobilisation preparation | D4: 2026-11-09 | E4: 2026-11-21 | F4: 0
A5: 4 | B5: G03 | C5: Pre-engineering survey campaign | D5: 2026-11-21 | E5: 2026-12-06 | F5: 1
A6: 5 | B6: G04 | C6: Survey reports, geometry/condition reconciliation | D6: 2026-12-07 | E6: 2026-12-12 | F6: 0
A7: 6 | B7: G05 | C7: Survey/basis review and comment closure allowance | D7: 2026-12-14 | E7: 2026-12-26 | F7: 0
A8: 7 | B8: B05-BAS | C8: Design basis, loads and interfaces | D8: 2026-12-28 | E8: 2027-01-02 | F8: 0
A9: 8 | B9: B05-BRV | C9: Basis review and comment closure allowance | D9: 2027-01-04 | E9: 2027-01-16 | F9: 0
A10: 9 | B10: B05-ANA | C10: Bridge/platform and preservice analysis preparation | D10: 2027-01-18 | E10: 2027-02-13 | F10: 0
A11: 10 | B11: B05-ARV | C11: Analysis review and comment closure allowance | D11: 2027-02-15 | E11: 2027-02-27 | F11: 0
A12: 11 | B12: B05-DET | C12: Connection, bearing, landing and workpack detailing | D12: 2027-03-01 | E12: 2027-03-20 | F12: 0
A13: 12 | B13: B05-DRV | C13: Drawing review and comment closure allowance | D13: 2027-03-22 | E13: 2027-04-03 | F13: 0
... A36: 35 | B36: FINISH | C36: Proposed contract-completion milestone | D36: 2028-04-06 | E36: 2028-04-06 | F36: 0

Sheet Schedule Scenarios
A1: Scenario | B1: Bays | C1: MT per bay-day | D1: Steel lead calendar days | E1: Finish exclusive | F1: Calendar days beyond assumed anniversary | G1: Evidence status
A2: BASE | B2: 2 | C2: 4 | D2: 45 | E2: 2028-04-06 | F2: 157 | G2: All capacity/lead-time assumptions unverified; not contractual delay entitlement
A3: MORE_YARD | B3: 4 | C3: 8 | D3: 45 | E3: 2028-02-26 | F3: 117 | G3: All capacity/lead-time assumptions unverified; not contractual delay entitlement
A4: FAST_SUPPLY_MORE_YARD | B4: 4 | C4: 8 | D4: 15 | E4: 2028-02-26 | F4: 117 | G4: All capacity/lead-time assumptions unverified; not contractual delay entitlement

Sheet Calendars and Method
A1: Control | B1: Rule
A2: OFFICE | B2: Mon–Fri8h; holidays absent
A3: YARD | B3: Mon–Sat; unverified shift/capacity
A4: OFF | B4: 7days;16May–15Oct blocked as planning scenario, indivisible work phase must fit open season
A5: ALL | B5: 7calendar days
A6: Date convention | B6: Half-open intervals: finish is next-day boundary; zero duration milestones at boundary
A7: Links | B7: FS0 including explicit proposed resource-sequencing links
A8: Offshore season | B8: Planning exclusion16May–15Oct; offshore phase indivisible; qualifying contractual relief needs actual evidence
A9: Capacity limitation | B9: Named chains only; engineering/NDT/POB/access/charter actual capacity unverified; not a full resource-feasibility result
A10: Float | B10: Calendar-day latest-start slack to scenario completion, not float against approved contractual dates
A11: Target comparison | B11: 1Nov2027 is assumed12month anniversary; convention and relief require contracts confirmation
A12: Algorithm checks | B12: All IDs/predecessors valid, DAG/cycle check, forward/backward dates, nonnegative computed float, FS constraints
A13: Sensitivity limitation | B13: Three deterministic scenarios; no probabilisticP80 or quantified contingency claim

Sheet Risk Register
A1: ID | B1: Event | C1: Early warning | D1: Owner | E1: Required mitigation | F1: Hold/escalation | G1: Likelihood | H1: Impact | I1: Residual exposure
A2: R01 | B2: Wrong source revision or unrelated S&SRP scope | C2: Revised SCC/A3 not positively mapped; common platform names | D2: Contracts | E2: Freeze affected release and resolve applicability/precedence | F2: PO/AFC release blocked for disputed requirement | I2: NOT QUANTIFIED
A3: R02 | B3: Survey geometry or corrosion differs from tender | C3: Span/elevation/thickness/support condition outside accepted model | D3: Engineering | E3: Survey, NDT, independent check and controlled redesign | F3: Affected design and load-path release held | I3: NOT QUANTIFIED
A4: R03 | B4: Steel grade/origin unavailable in lead time | C4: Mill quote fails grade, dimensions or Melt&Pour/DVA evidence | D4: Procurement | E4: Qualify alternative compliant mill/section through design approval | F4: No unauthorised substitution | I4: NOT QUANTIFIED
A5: R04 | B5: First offshore season missed | C5: Ready-for-installation forecast beyond15May under scenario | D5: Planning | E5: Stage independent releases and verify earlier supply/capacity; cost second season | F5: Seek schedule/contract decision with evidence | I5: NOT QUANTIFIED
A6: R05 | B6: Vessel capacity or availability fails | C6: Crane chart, deck/stability or booking does not cover module | D6: Marine | E6: Engineer module envelope and qualify alternate spread | F6: No charter/lift commitment without assurance | I6: NOT QUANTIFIED
A7: R06 | B7: Shared crews/yard bottleneck | C7: Weekly demand exceeds named capacity or coating/NDT queue grows | D7: Construction | E7: Resource loading, workfront sequencing and priced additional capacity | F7: Escalate before lookahead freeze | I7: NOT QUANTIFIED
A8: R07 | B8: Piping/platform movement mismatch | C8: Stress/support reactions not accepted by structural team | D8: Piping/Structural | E8: Iterate movement/stiffness and supporting deck checks | F8: Bearing/service design release held | I8: NOT QUANTIFIED
A9: R08 | B9: Live-service loss or unsafe demolition | C9: Isolation/bypass/temporary support not accepted | D9: Operations | E9: Integrated SIMOPS/transfer and staged stability review | F9: Stop affected work; complete controlled readiness | I9: NOT QUANTIFIED
A10: R09 | B10: NDT/coating rework or curing delays | C10: Rejects, environment or DFT outside approved procedure | D10: QA | E10: Qualify process, monitor environment, inspect and repair | F10: No loadout before release | I10: NOT QUANTIFIED
A11: R10 | B11: Funding shortfall | C11: Unpriced charters, unverified receipts or late certification | D11: Finance | E11: Priced estimate, full-life cash, committed facility and scenario stress | F11: Spending within authorised funded ceiling | I11: NOT QUANTIFIED
A12: R11 | B12: Measurement/payment rejection | C12: No accepted e-MB/SES or amended milestone evidence | D12: Controls | E12: Contemporaneous measurements and invoice reconciliation | F12: Correct records before billing claim | I12: NOT QUANTIFIED
A13: R12 | B13: Emergency/weather disruption | C13: Forecast reaches abort thresholds or vessel critical system fails | D13: Marine/HSE | E13: Refuge/evacuation plan, drills, stop/abort authority and reserve strategy | F13: Record decision and personnel accountability | I13: NOT QUANTIFIED

Sheet QA and Release Gates
A1: Gate | B1: Prerequisite evidence | C1: Accountable | D1: Release authority | E1: Status
A2: Survey/basis | B2: Accepted survey, source hierarchy and design queries | C2: Engineering | D2: Project authority/company/CA as contract applies | E2: HOLD — evidence not supplied
A3: Design release | B3: Checked analysis, connection/bearing/stage checks and matching drawings | C3: Engineering | D3: Project authority/company/CA as contract applies | E3: HOLD — evidence not supplied
A4: Purchase release | B4: ApprovedPS, origin/compliance and authorised cost commitment | C4: Procurement | D4: Project authority/company/CA as contract applies | E4: HOLD — evidence not supplied
A5: Weld start | B5: ApprovedWPS/PQR, welder qualifications, material identity | C5: QA | D5: Project authority/company/CA as contract applies | E5: HOLD — evidence not supplied
A6: NDT release | B6: Accepted procedure/personnel/calibration/reports and repair closure | C6: QA | D6: Project authority/company/CA as contract applies | E6: HOLD — evidence not supplied
A7: Coating start | B7: Approved system, surface condition, environment and hold-point release | C7: QA | D7: Project authority/company/CA as contract applies | E7: HOLD — evidence not supplied
A8: Loadout | B8: Dimensions, weight/COG, trial fit, lifting and transport assurance | C8: Marine | D8: Project authority/company/CA as contract applies | E8: HOLD — evidence not supplied
A9: Sailout | B9: Vessel certificates/audit, cargo/seafastening and readiness | C9: Marine | D9: Project authority/company/CA as contract applies | E9: HOLD — evidence not supplied
A10: Installation | B10: PTW/SIMOPS/support readiness, weather and approved lift plan | C10: Construction | D10: Project authority/company/CA as contract applies | E10: HOLD — evidence not supplied
A11: Removal | B11: Accepted alternate support/service configuration and engineered sequence | C11: Construction | D11: Project authority/company/CA as contract applies | E11: HOLD — evidence not supplied
A12: Reinstatement | B12: Approved test boundaries/results and operations authorisation | C12: Commissioning | D12: Project authority/company/CA as contract applies | E12: HOLD — evidence not supplied
A13: Turnover | B13: As-builts, inspection records, punch closure and formal acceptance | C13: Completions | D13: Project authority/company/CA as contract applies | E13: HOLD — evidence not supplied

Sheet Marine Assurance
A1: Operation | B1: Required engineered checks | C1: Required records | D1: Status
A2: Module definition | B2: Dimensions, centre of gravity, attachments, loose items and tolerances | C2: Weight report/drawing revision | D2: OPEN
A3: Lift | B3: Crane at radius/configuration; dynamics, rigging/load share, padeyes and local structure | C3: Independent checked lift pack; certified gear | D3: OPEN
A4: Loadout/voyage | B4: Deck capacity/stability, supports, accelerations, seafastening, route/forecast | C4: Loadout/voyage approval and survey | D4: OPEN
A5: Positioning | B5: Mooring/DP, clearance, seabed/caisson risks, operational limits | C5: Approved positioning/anchor plan | D5: OPEN
A6: Landing | B6: Movement/thrust, support strength, alignment, bearing setting and restraint removal | C6: Survey, support release and ITR | D6: OPEN
A7: Demolition | B7: Stage-by-stage load path, temporary support, cut/lift points and services | C7: Accepted removal pack and permit | D7: OPEN
A8: Personnel | B8: POB/certificates/medical/training, transfer and evacuation | C8: C9/C10 audit and emergency records | D8: OPEN

Sheet HSE and SIMOPS
A1: Hazard/control | B1: Minimum evidence | C1: Owner | D1: Status
A2: Isolation/LOTO | B2: Approved boundary, register, gas tests and operations verification | C2: HSE/Operations | D2: OPEN
A3: Hot work | B3: Permit, gas monitoring, fire watch and extinguisher provision | C3: HSE/Operations | D3: OPEN
A4: Working at height | B4: Certified access, harness/anchors and rescue plan | C4: HSE/Operations | D4: OPEN
A5: Lifting/dropped objects | B5: Engineered lifts, exclusion zone, communications and tool control | C5: HSE/Operations | D5: OPEN
A6: Scaffolding | B6: Design/load class, tags, inspection and rescue access | C6: HSE/Operations | D6: OPEN
A7: Marine transfers | B7: Vessel/platform interface, personnel transfer limits and certification | C7: HSE/Operations | D7: OPEN
A8: Coating/chemicals | B8: SDS, ventilation, respiratory/skin protection and exposure controls | C8: HSE/Operations | D8: OPEN
A9: Noise/manual handling | B9: Assessment, protection and handling methods | C9: HSE/Operations | D9: OPEN
A10: PPE | B10: Certified issuance/replacement matrix before work | C10: HSE/Operations | D10: OPEN
A11: Emergency | B11: Platform/vessel command, muster/POB, medevac and joint drills | C11: HSE/Operations | D11: OPEN
A12: Electrical | B12: Approved isolation, competent persons and certified equipment | C12: HSE/Operations | D12: OPEN
A13: Environmental | B13: Spill prevention, waste segregation, scrap and disposal records | C13: HSE/Operations | D13: OPEN

Sheet Daily Production
A1: Date | B1: IWP | C1: Planned quantity | D1: Accepted quantity | E1: Unit | F1: Actual crew-hours | G1: Nonproductive hours | H1: Rework quantity | I1: Acceptance record | J1: Constraint | K1: Responsible

Sheet Progress Rules
A1: Workstream | B1: Proposed or contractual basis | C1: Evidence | D1: Guardrail
A2: Engineering | B2: C8 review dispositionC=0/B=60/A=100 on applicable engineering item basis | C2: Accepted projectDCI and review status | D2: Not overall-project or cash percentage
A3: Procurement | B3: C8 two-stagePS5%+5% of applicable procurement-item weight | C3: MCI applicability and stage approvals | D3: Not10% of contract value
A4: Fabrication | B4: Accepted BOM/weld/tonnage stages under approved rules | C4: Material/weld/NDT/dimension records | D4: No double count with offshore installation
A5: Installation | B5: Accepted installed work quantities and test stages | C5: ITRs/e-MB/service acceptance | D5: Exclude rejected/rework quantities
A6: Turnover | B6: Accepted dossiers and contractual milestone | C6: Company acceptance | D6: Submission alone does not equal acceptance
A7: EVM | B7: EV=approvedBAC×approved accepted progress;SPI=EV/PV;CPI=EV/AC | C7: PricedBAC,timephasedPV,actualAC | D7: Do not calculate without these inputs

Sheet Cost Commitments
A1: Package | B1: Approved budget INR | C1: PO commitment INR | D1: Accrued unpaid INR | E1: Actual paid INR | F1: Forecast remaining INR | G1: Forecast total INR | H1: Quote/evidence | I1: Owner
A2: STEEL-B01 | G2: =IF(COUNT(E2:F2)<2,"",SUM(E2:F2)) | I2: Procurement
A3: STEEL-B02 | G3: =IF(COUNT(E3:F3)<2,"",SUM(E3:F3)) | I3: Procurement
A4: STEEL-B03 | G4: =IF(COUNT(E4:F4)<2,"",SUM(E4:F4)) | I4: Procurement
A5: STEEL-B04 | G5: =IF(COUNT(E5:F5)<2,"",SUM(E5:F5)) | I5: Procurement
A6: STEEL-B05 | G6: =IF(COUNT(E6:F6)<2,"",SUM(E6:F6)) | I6: Procurement
A7: STEEL-B06 | G7: =IF(COUNT(E7:F7)<2,"",SUM(E7:F7)) | I7: Procurement
A8: STEEL-B07 | G8: =IF(COUNT(E8:F8)<2,"",SUM(E8:F8)) | I8: Procurement
A9: STEEL-B08 | G9: =IF(COUNT(E9:F9)<2,"",SUM(E9:F9)) | I9: Procurement
A10: STEEL-B09 | G10: =IF(COUNT(E10:F10)<2,"",SUM(E10:F10)) | I10: Procurement
A11: STEEL-B10 | G11: =IF(COUNT(E11:F11)<2,"",SUM(E11:F11)) | I11: Procurement
A12: BEAR | G12: =IF(COUNT(E12:F12)<2,"",SUM(E12:F12)) | I12: Engineering
A13: GRAT | G13: =IF(COUNT(E13:F13)<2,"",SUM(E13:F13)) | I13: Procurement
... A26: TRAY | G26: =IF(COUNT(E26:F26)<2,"",SUM(E26:F26)) | I26: Electrical

Sheet Financial Basis
A1: Input / control | B1: Value | C1: Instruction
A2: Opening available project cash INR | C2: Enter funded amount and evidence; blank is unknown
A3: Contract value INR | C3: Verified bid/award amount; do not infer from qualification threshold
A4: Status | B4: UNPRICED | C4: No financial-feasibility conclusion
A5: EAC convention | B5: Actual paid plus all forecast remaining | C5: Remaining must include accrued unpaid, open commitments and uncommittedETC without duplication
A6: Horizon | B6: 156weeks, extend if required | C6: Include actual warranty/retention/security/final-account dates;156weeks is not proof every obligation ends
A7: Receipts | B7: Actual contract milestones and payment lags | C7: Deleted separate mob/demob payments excluded unless governing amendment states otherwise
A8: Tax | B8: Transaction-specific GST/customs/TDS/credits | C8: Gross invoice, net receipt and recoverable tax separate
A9: Security | B9: Guarantee face value differs from margin cash/fees | C9: Track expiry, bank commission and margin release independently

Sheet 156 Week Cash
A1: Week | B1: Scenario week start | C1: Contract receipts INR | D1: Retention/security cash release | E1: Other cash-in | F1: Vendor/subcontract payments | G1: Wages/overheads | H1: Marine/logistics | I1: Tax/financing/BG margin | J1: Other cash-out | K1: Net cash | L1: Cumulative net cash | M1: Cash incl opening | N1: Verification status: VERIFIED only after all8inputs evidenced
A2: 1 | B2: 2026-11-01 | K2: =IF(OR(N2<>"VERIFIED",COUNT(C2:J2)<8),"",SUM(C2:E2)-SUM(F2:J2)) | L2: =IF(COUNT(K$2:K2)<1,"",SUM(K$2:K2)) | M2: =IF(OR('Financial Basis'!B2="",L2=""),"",'Financial Basis'!B2+L2)
A3: 2 | B3: 2026-11-08 | K3: =IF(OR(N3<>"VERIFIED",COUNT(C3:J3)<8),"",SUM(C3:E3)-SUM(F3:J3)) | L3: =IF(COUNT(K$2:K3)<2,"",SUM(K$2:K3)) | M3: =IF(OR('Financial Basis'!B2="",L3=""),"",'Financial Basis'!B2+L3)
A4: 3 | B4: 2026-11-15 | K4: =IF(OR(N4<>"VERIFIED",COUNT(C4:J4)<8),"",SUM(C4:E4)-SUM(F4:J4)) | L4: =IF(COUNT(K$2:K4)<3,"",SUM(K$2:K4)) | M4: =IF(OR('Financial Basis'!B2="",L4=""),"",'Financial Basis'!B2+L4)
A5: 4 | B5: 2026-11-22 | K5: =IF(OR(N5<>"VERIFIED",COUNT(C5:J5)<8),"",SUM(C5:E5)-SUM(F5:J5)) | L5: =IF(COUNT(K$2:K5)<4,"",SUM(K$2:K5)) | M5: =IF(OR('Financial Basis'!B2="",L5=""),"",'Financial Basis'!B2+L5)
A6: 5 | B6: 2026-11-29 | K6: =IF(OR(N6<>"VERIFIED",COUNT(C6:J6)<8),"",SUM(C6:E6)-SUM(F6:J6)) | L6: =IF(COUNT(K$2:K6)<5,"",SUM(K$2:K6)) | M6: =IF(OR('Financial Basis'!B2="",L6=""),"",'Financial Basis'!B2+L6)
A7: 6 | B7: 2026-12-06 | K7: =IF(OR(N7<>"VERIFIED",COUNT(C7:J7)<8),"",SUM(C7:E7)-SUM(F7:J7)) | L7: =IF(COUNT(K$2:K7)<6,"",SUM(K$2:K7)) | M7: =IF(OR('Financial Basis'!B2="",L7=""),"",'Financial Basis'!B2+L7)
A8: 7 | B8: 2026-12-13 | K8: =IF(OR(N8<>"VERIFIED",COUNT(C8:J8)<8),"",SUM(C8:E8)-SUM(F8:J8)) | L8: =IF(COUNT(K$2:K8)<7,"",SUM(K$2:K8)) | M8: =IF(OR('Financial Basis'!B2="",L8=""),"",'Financial Basis'!B2+L8)
A9: 8 | B9: 2026-12-20 | K9: =IF(OR(N9<>"VERIFIED",COUNT(C9:J9)<8),"",SUM(C9:E9)-SUM(F9:J9)) | L9: =IF(COUNT(K$2:K9)<8,"",SUM(K$2:K9)) | M9: =IF(OR('Financial Basis'!B2="",L9=""),"",'Financial Basis'!B2+L9)
A10: 9 | B10: 2026-12-27 | K10: =IF(OR(N10<>"VERIFIED",COUNT(C10:J10)<8),"",SUM(C10:E10)-SUM(F10:J10)) | L10: =IF(COUNT(K$2:K10)<9,"",SUM(K$2:K10)) | M10: =IF(OR('Financial Basis'!B2="",L10=""),"",'Financial Basis'!B2+L10)
A11: 10 | B11: 2027-01-03 | K11: =IF(OR(N11<>"VERIFIED",COUNT(C11:J11)<8),"",SUM(C11:E11)-SUM(F11:J11)) | L11: =IF(COUNT(K$2:K11)<10,"",SUM(K$2:K11)) | M11: =IF(OR('Financial Basis'!B2="",L11=""),"",'Financial Basis'!B2+L11)
A12: 11 | B12: 2027-01-10 | K12: =IF(OR(N12<>"VERIFIED",COUNT(C12:J12)<8),"",SUM(C12:E12)-SUM(F12:J12)) | L12: =IF(COUNT(K$2:K12)<11,"",SUM(K$2:K12)) | M12: =IF(OR('Financial Basis'!B2="",L12=""),"",'Financial Basis'!B2+L12)
A13: 12 | B13: 2027-01-17 | K13: =IF(OR(N13<>"VERIFIED",COUNT(C13:J13)<8),"",SUM(C13:E13)-SUM(F13:J13)) | L13: =IF(COUNT(K$2:K13)<12,"",SUM(K$2:K13)) | M13: =IF(OR('Financial Basis'!B2="",L13=""),"",'Financial Basis'!B2+L13)
A14: 13 | B14: 2027-01-24 | K14: =IF(OR(N14<>"VERIFIED",COUNT(C14:J14)<8),"",SUM(C14:E14)-SUM(F14:J14)) | L14: =IF(COUNT(K$2:K14)<13,"",SUM(K$2:K14)) | M14: =IF(OR('Financial Basis'!B2="",L14=""),"",'Financial Basis'!B2+L14)
A15: 14 | B15: 2027-01-31 | K15: =IF(OR(N15<>"VERIFIED",COUNT(C15:J15)<8),"",SUM(C15:E15)-SUM(F15:J15)) | L15: =IF(COUNT(K$2:K15)<14,"",SUM(K$2:K15)) | M15: =IF(OR('Financial Basis'!B2="",L15=""),"",'Financial Basis'!B2+L15)
A16: 15 | B16: 2027-02-07 | K16: =IF(OR(N16<>"VERIFIED",COUNT(C16:J16)<8),"",SUM(C16:E16)-SUM(F16:J16)) | L16: =IF(COUNT(K$2:K16)<15,"",SUM(K$2:K16)) | M16: =IF(OR('Financial Basis'!B2="",L16=""),"",'Financial Basis'!B2+L16)
A17: 16 | B17: 2027-02-14 | K17: =IF(OR(N17<>"VERIFIED",COUNT(C17:J17)<8),"",SUM(C17:E17)-SUM(F17:J17)) | L17: =IF(COUNT(K$2:K17)<16,"",SUM(K$2:K17)) | M17: =IF(OR('Financial Basis'!B2="",L17=""),"",'Financial Basis'!B2+L17)
A18: 17 | B18: 2027-02-21 | K18: =IF(OR(N18<>"VERIFIED",COUNT(C18:J18)<8),"",SUM(C18:E18)-SUM(F18:J18)) | L18: =IF(COUNT(K$2:K18)<17,"",SUM(K$2:K18)) | M18: =IF(OR('Financial Basis'!B2="",L18=""),"",'Financial Basis'!B2+L18)
A19: 18 | B19: 2027-02-28 | K19: =IF(OR(N19<>"VERIFIED",COUNT(C19:J19)<8),"",SUM(C19:E19)-SUM(F19:J19)) | L19: =IF(COUNT(K$2:K19)<18,"",SUM(K$2:K19)) | M19: =IF(OR('Financial Basis'!B2="",L19=""),"",'Financial Basis'!B2+L19)
A20: 19 | B20: 2027-03-07 | K20: =IF(OR(N20<>"VERIFIED",COUNT(C20:J20)<8),"",SUM(C20:E20)-SUM(F20:J20)) | L20: =IF(COUNT(K$2:K20)<19,"",SUM(K$2:K20)) | M20: =IF(OR('Financial Basis'!B2="",L20=""),"",'Financial Basis'!B2+L20)
A21: 20 | B21: 2027-03-14 | K21: =IF(OR(N21<>"VERIFIED",COUNT(C21:J21)<8),"",SUM(C21:E21)-SUM(F21:J21)) | L21: =IF(COUNT(K$2:K21)<20,"",SUM(K$2:K21)) | M21: =IF(OR('Financial Basis'!B2="",L21=""),"",'Financial Basis'!B2+L21)
A22: 21 | B22: 2027-03-21 | K22: =IF(OR(N22<>"VERIFIED",COUNT(C22:J22)<8),"",SUM(C22:E22)-SUM(F22:J22)) | L22: =IF(COUNT(K$2:K22)<21,"",SUM(K$2:K22)) | M22: =IF(OR('Financial Basis'!B2="",L22=""),"",'Financial Basis'!B2+L22)
A23: 22 | B23: 2027-03-28 | K23: =IF(OR(N23<>"VERIFIED",COUNT(C23:J23)<8),"",SUM(C23:E23)-SUM(F23:J23)) | L23: =IF(COUNT(K$2:K23)<22,"",SUM(K$2:K23)) | M23: =IF(OR('Financial Basis'!B2="",L23=""),"",'Financial Basis'!B2+L23)
A24: 23 | B24: 2027-04-04 | K24: =IF(OR(N24<>"VERIFIED",COUNT(C24:J24)<8),"",SUM(C24:E24)-SUM(F24:J24)) | L24: =IF(COUNT(K$2:K24)<23,"",SUM(K$2:K24)) | M24: =IF(OR('Financial Basis'!B2="",L24=""),"",'Financial Basis'!B2+L24)
A25: 24 | B25: 2027-04-11 | K25: =IF(OR(N25<>"VERIFIED",COUNT(C25:J25)<8),"",SUM(C25:E25)-SUM(F25:J25)) | L25: =IF(COUNT(K$2:K25)<24,"",SUM(K$2:K25)) | M25: =IF(OR('Financial Basis'!B2="",L25=""),"",'Financial Basis'!B2+L25)
A26: 25 | B26: 2027-04-18 | K26: =IF(OR(N26<>"VERIFIED",COUNT(C26:J26)<8),"",SUM(C26:E26)-SUM(F26:J26)) | L26: =IF(COUNT(K$2:K26)<25,"",SUM(K$2:K26)) | M26: =IF(OR('Financial Basis'!B2="",L26=""),"",'Financial Basis'!B2+L26)
A27: 26 | B27: 2027-04-25 | K27: =IF(OR(N27<>"VERIFIED",COUNT(C27:J27)<8),"",SUM(C27:E27)-SUM(F27:J27)) | L27: =IF(COUNT(K$2:K27)<26,"",SUM(K$2:K27)) | M27: =IF(OR('Financial Basis'!B2="",L27=""),"",'Financial Basis'!B2+L27)
A28: 27 | B28: 2027-05-02 | K28: =IF(OR(N28<>"VERIFIED",COUNT(C28:J28)<8),"",SUM(C28:E28)-SUM(F28:J28)) | L28: =IF(COUNT(K$2:K28)<27,"",SUM(K$2:K28)) | M28: =IF(OR('Financial Basis'!B2="",L28=""),"",'Financial Basis'!B2+L28)
A29: 28 | B29: 2027-05-09 | K29: =IF(OR(N29<>"VERIFIED",COUNT(C29:J29)<8),"",SUM(C29:E29)-SUM(F29:J29)) | L29: =IF(COUNT(K$2:K29)<28,"",SUM(K$2:K29)) | M29: =IF(OR('Financial Basis'!B2="",L29=""),"",'Financial Basis'!B2+L29)
A30: 29 | B30: 2027-05-16 | K30: =IF(OR(N30<>"VERIFIED",COUNT(C30:J30)<8),"",SUM(C30:E30)-SUM(F30:J30)) | L30: =IF(COUNT(K$2:K30)<29,"",SUM(K$2:K30)) | M30: =IF(OR('Financial Basis'!B2="",L30=""),"",'Financial Basis'!B2+L30)
A31: 30 | B31: 2027-05-23 | K31: =IF(OR(N31<>"VERIFIED",COUNT(C31:J31)<8),"",SUM(C31:E31)-SUM(F31:J31)) | L31: =IF(COUNT(K$2:K31)<30,"",SUM(K$2:K31)) | M31: =IF(OR('Financial Basis'!B2="",L31=""),"",'Financial Basis'!B2+L31)
A32: 31 | B32: 2027-05-30 | K32: =IF(OR(N32<>"VERIFIED",COUNT(C32:J32)<8),"",SUM(C32:E32)-SUM(F32:J32)) | L32: =IF(COUNT(K$2:K32)<31,"",SUM(K$2:K32)) | M32: =IF(OR('Financial Basis'!B2="",L32=""),"",'Financial Basis'!B2+L32)
A33: 32 | B33: 2027-06-06 | K33: =IF(OR(N33<>"VERIFIED",COUNT(C33:J33)<8),"",SUM(C33:E33)-SUM(F33:J33)) | L33: =IF(COUNT(K$2:K33)<32,"",SUM(K$2:K33)) | M33: =IF(OR('Financial Basis'!B2="",L33=""),"",'Financial Basis'!B2+L33)
A34: 33 | B34: 2027-06-13 | K34: =IF(OR(N34<>"VERIFIED",COUNT(C34:J34)<8),"",SUM(C34:E34)-SUM(F34:J34)) | L34: =IF(COUNT(K$2:K34)<33,"",SUM(K$2:K34)) | M34: =IF(OR('Financial Basis'!B2="",L34=""),"",'Financial Basis'!B2+L34)
A35: 34 | B35: 2027-06-20 | K35: =IF(OR(N35<>"VERIFIED",COUNT(C35:J35)<8),"",SUM(C35:E35)-SUM(F35:J35)) | L35: =IF(COUNT(K$2:K35)<34,"",SUM(K$2:K35)) | M35: =IF(OR('Financial Basis'!B2="",L35=""),"",'Financial Basis'!B2+L35)
A36: 35 | B36: 2027-06-27 | K36: =IF(OR(N36<>"VERIFIED",COUNT(C36:J36)<8),"",SUM(C36:E36)-SUM(F36:J36)) | L36: =IF(COUNT(K$2:K36)<35,"",SUM(K$2:K36)) | M36: =IF(OR('Financial Basis'!B2="",L36=""),"",'Financial Basis'!B2+L36)
A37: 36 | B37: 2027-07-04 | K37: =IF(OR(N37<>"VERIFIED",COUNT(C37:J37)<8),"",SUM(C37:E37)-SUM(F37:J37)) | L37: =IF(COUNT(K$2:K37)<36,"",SUM(K$2:K37)) | M37: =IF(OR('Financial Basis'!B2="",L37=""),"",'Financial Basis'!B2+L37)
A38: 37 | B38: 2027-07-11 | K38: =IF(OR(N38<>"VERIFIED",COUNT(C38:J38)<8),"",SUM(C38:E38)-SUM(F38:J38)) | L38: =IF(COUNT(K$2:K38)<37,"",SUM(K$2:K38)) | M38: =IF(OR('Financial Basis'!B2="",L38=""),"",'Financial Basis'!B2+L38)
A39: 38 | B39: 2027-07-18 | K39: =IF(OR(N39<>"VERIFIED",COUNT(C39:J39)<8),"",SUM(C39:E39)-SUM(F39:J39)) | L39: =IF(COUNT(K$2:K39)<38,"",SUM(K$2:K39)) | M39: =IF(OR('Financial Basis'!B2="",L39=""),"",'Financial Basis'!B2+L39)
A40: 39 | B40: 2027-07-25 | K40: =IF(OR(N40<>"VERIFIED",COUNT(C40:J40)<8),"",SUM(C40:E40)-SUM(F40:J40)) | L40: =IF(COUNT(K$2:K40)<39,"",SUM(K$2:K40)) | M40: =IF(OR('Financial Basis'!B2="",L40=""),"",'Financial Basis'!B2+L40)
A41: 40 | B41: 2027-08-01 | K41: =IF(OR(N41<>"VERIFIED",COUNT(C41:J41)<8),"",SUM(C41:E41)-SUM(F41:J41)) | L41: =IF(COUNT(K$2:K41)<40,"",SUM(K$2:K41)) | M41: =IF(OR('Financial Basis'!B2="",L41=""),"",'Financial Basis'!B2+L41)
A42: 41 | B42: 2027-08-08 | K42: =IF(OR(N42<>"VERIFIED",COUNT(C42:J42)<8),"",SUM(C42:E42)-SUM(F42:J42)) | L42: =IF(COUNT(K$2:K42)<41,"",SUM(K$2:K42)) | M42: =IF(OR('Financial Basis'!B2="",L42=""),"",'Financial Basis'!B2+L42)
A43: 42 | B43: 2027-08-15 | K43: =IF(OR(N43<>"VERIFIED",COUNT(C43:J43)<8),"",SUM(C43:E43)-SUM(F43:J43)) | L43: =IF(COUNT(K$2:K43)<42,"",SUM(K$2:K43)) | M43: =IF(OR('Financial Basis'!B2="",L43=""),"",'Financial Basis'!B2+L43)
A44: 43 | B44: 2027-08-22 | K44: =IF(OR(N44<>"VERIFIED",COUNT(C44:J44)<8),"",SUM(C44:E44)-SUM(F44:J44)) | L44: =IF(COUNT(K$2:K44)<43,"",SUM(K$2:K44)) | M44: =IF(OR('Financial Basis'!B2="",L44=""),"",'Financial Basis'!B2+L44)
A45: 44 | B45: 2027-08-29 | K45: =IF(OR(N45<>"VERIFIED",COUNT(C45:J45)<8),"",SUM(C45:E45)-SUM(F45:J45)) | L45: =IF(COUNT(K$2:K45)<44,"",SUM(K$2:K45)) | M45: =IF(OR('Financial Basis'!B2="",L45=""),"",'Financial Basis'!B2+L45)
A46: 45 | B46: 2027-09-05 | K46: =IF(OR(N46<>"VERIFIED",COUNT(C46:J46)<8),"",SUM(C46:E46)-SUM(F46:J46)) | L46: =IF(COUNT(K$2:K46)<45,"",SUM(K$2:K46)) | M46: =IF(OR('Financial Basis'!B2="",L46=""),"",'Financial Basis'!B2+L46)
A47: 46 | B47: 2027-09-12 | K47: =IF(OR(N47<>"VERIFIED",COUNT(C47:J47)<8),"",SUM(C47:E47)-SUM(F47:J47)) | L47: =IF(COUNT(K$2:K47)<46,"",SUM(K$2:K47)) | M47: =IF(OR('Financial Basis'!B2="",L47=""),"",'Financial Basis'!B2+L47)
A48: 47 | B48: 2027-09-19 | K48: =IF(OR(N48<>"VERIFIED",COUNT(C48:J48)<8),"",SUM(C48:E48)-SUM(F48:J48)) | L48: =IF(COUNT(K$2:K48)<47,"",SUM(K$2:K48)) | M48: =IF(OR('Financial Basis'!B2="",L48=""),"",'Financial Basis'!B2+L48)
A49: 48 | B49: 2027-09-26 | K49: =IF(OR(N49<>"VERIFIED",COUNT(C49:J49)<8),"",SUM(C49:E49)-SUM(F49:J49)) | L49: =IF(COUNT(K$2:K49)<48,"",SUM(K$2:K49)) | M49: =IF(OR('Financial Basis'!B2="",L49=""),"",'Financial Basis'!B2+L49)
A50: 49 | B50: 2027-10-03 | K50: =IF(OR(N50<>"VERIFIED",COUNT(C50:J50)<8),"",SUM(C50:E50)-SUM(F50:J50)) | L50: =IF(COUNT(K$2:K50)<49,"",SUM(K$2:K50)) | M50: =IF(OR('Financial Basis'!B2="",L50=""),"",'Financial Basis'!B2+L50)
A51: 50 | B51: 2027-10-10 | K51: =IF(OR(N51<>"VERIFIED",COUNT(C51:J51)<8),"",SUM(C51:E51)-SUM(F51:J51)) | L51: =IF(COUNT(K$2:K51)<50,"",SUM(K$2:K51)) | M51: =IF(OR('Financial Basis'!B2="",L51=""),"",'Financial Basis'!B2+L51)
A52: 51 | B52: 2027-10-17 | K52: =IF(OR(N52<>"VERIFIED",COUNT(C52:J52)<8),"",SUM(C52:E52)-SUM(F52:J52)) | L52: =IF(COUNT(K$2:K52)<51,"",SUM(K$2:K52)) | M52: =IF(OR('Financial Basis'!B2="",L52=""),"",'Financial Basis'!B2+L52)
A53: 52 | B53: 2027-10-24 | K53: =IF(OR(N53<>"VERIFIED",COUNT(C53:J53)<8),"",SUM(C53:E53)-SUM(F53:J53)) | L53: =IF(COUNT(K$2:K53)<52,"",SUM(K$2:K53)) | M53: =IF(OR('Financial Basis'!B2="",L53=""),"",'Financial Basis'!B2+L53)
A54: 53 | B54: 2027-10-31 | K54: =IF(OR(N54<>"VERIFIED",COUNT(C54:J54)<8),"",SUM(C54:E54)-SUM(F54:J54)) | L54: =IF(COUNT(K$2:K54)<53,"",SUM(K$2:K54)) | M54: =IF(OR('Financial Basis'!B2="",L54=""),"",'Financial Basis'!B2+L54)
A55: 54 | B55: 2027-11-07 | K55: =IF(OR(N55<>"VERIFIED",COUNT(C55:J55)<8),"",SUM(C55:E55)-SUM(F55:J55)) | L55: =IF(COUNT(K$2:K55)<54,"",SUM(K$2:K55)) | M55: =IF(OR('Financial Basis'!B2="",L55=""),"",'Financial Basis'!B2+L55)
A56: 55 | B56: 2027-11-14 | K56: =IF(OR(N56<>"VERIFIED",COUNT(C56:J56)<8),"",SUM(C56:E56)-SUM(F56:J56)) | L56: =IF(COUNT(K$2:K56)<55,"",SUM(K$2:K56)) | M56: =IF(OR('Financial Basis'!B2="",L56=""),"",'Financial Basis'!B2+L56)
A57: 56 | B57: 2027-11-21 | K57: =IF(OR(N57<>"VERIFIED",COUNT(C57:J57)<8),"",SUM(C57:E57)-SUM(F57:J57)) | L57: =IF(COUNT(K$2:K57)<56,"",SUM(K$2:K57)) | M57: =IF(OR('Financial Basis'!B2="",L57=""),"",'Financial Basis'!B2+L57)
A58: 57 | B58: 2027-11-28 | K58: =IF(OR(N58<>"VERIFIED",COUNT(C58:J58)<8),"",SUM(C58:E58)-SUM(F58:J58)) | L58: =IF(COUNT(K$2:K58)<57,"",SUM(K$2:K58)) | M58: =IF(OR('Financial Basis'!B2="",L58=""),"",'Financial Basis'!B2+L58)
A59: 58 | B59: 2027-12-05 | K59: =IF(OR(N59<>"VERIFIED",COUNT(C59:J59)<8),"",SUM(C59:E59)-SUM(F59:J59)) | L59: =IF(COUNT(K$2:K59)<58,"",SUM(K$2:K59)) | M59: =IF(OR('Financial Basis'!B2="",L59=""),"",'Financial Basis'!B2+L59)
A60: 59 | B60: 2027-12-12 | K60: =IF(OR(N60<>"VERIFIED",COUNT(C60:J60)<8),"",SUM(C60:E60)-SUM(F60:J60)) | L60: =IF(COUNT(K$2:K60)<59,"",SUM(K$2:K60)) | M60: =IF(OR('Financial Basis'!B2="",L60=""),"",'Financial Basis'!B2+L60)
A61: 60 | B61: 2027-12-19 | K61: =IF(OR(N61<>"VERIFIED",COUNT(C61:J61)<8),"",SUM(C61:E61)-SUM(F61:J61)) | L61: =IF(COUNT(K$2:K61)<60,"",SUM(K$2:K61)) | M61: =IF(OR('Financial Basis'!B2="",L61=""),"",'Financial Basis'!B2+L61)
A62: 61 | B62: 2027-12-26 | K62: =IF(OR(N62<>"VERIFIED",COUNT(C62:J62)<8),"",SUM(C62:E62)-SUM(F62:J62)) | L62: =IF(COUNT(K$2:K62)<61,"",SUM(K$2:K62)) | M62: =IF(OR('Financial Basis'!B2="",L62=""),"",'Financial Basis'!B2+L62)
A63: 62 | B63: 2028-01-02 | K63: =IF(OR(N63<>"VERIFIED",COUNT(C63:J63)<8),"",SUM(C63:E63)-SUM(F63:J63)) | L63: =IF(COUNT(K$2:K63)<62,"",SUM(K$2:K63)) | M63: =IF(OR('Financial Basis'!B2="",L63=""),"",'Financial Basis'!B2+L63)
A64: 63 | B64: 2028-01-09 | K64: =IF(OR(N64<>"VERIFIED",COUNT(C64:J64)<8),"",SUM(C64:E64)-SUM(F64:J64)) | L64: =IF(COUNT(K$2:K64)<63,"",SUM(K$2:K64)) | M64: =IF(OR('Financial Basis'!B2="",L64=""),"",'Financial Basis'!B2+L64)
A65: 64 | B65: 2028-01-16 | K65: =IF(OR(N65<>"VERIFIED",COUNT(C65:J65)<8),"",SUM(C65:E65)-SUM(F65:J65)) | L65: =IF(COUNT(K$2:K65)<64,"",SUM(K$2:K65)) | M65: =IF(OR('Financial Basis'!B2="",L65=""),"",'Financial Basis'!B2+L65)
A66: 65 | B66: 2028-01-23 | K66: =IF(OR(N66<>"VERIFIED",COUNT(C66:J66)<8),"",SUM(C66:E66)-SUM(F66:J66)) | L66: =IF(COUNT(K$2:K66)<65,"",SUM(K$2:K66)) | M66: =IF(OR('Financial Basis'!B2="",L66=""),"",'Financial Basis'!B2+L66)
A67: 66 | B67: 2028-01-30 | K67: =IF(OR(N67<>"VERIFIED",COUNT(C67:J67)<8),"",SUM(C67:E67)-SUM(F67:J67)) | L67: =IF(COUNT(K$2:K67)<66,"",SUM(K$2:K67)) | M67: =IF(OR('Financial Basis'!B2="",L67=""),"",'Financial Basis'!B2+L67)
A68: 67 | B68: 2028-02-06 | K68: =IF(OR(N68<>"VERIFIED",COUNT(C68:J68)<8),"",SUM(C68:E68)-SUM(F68:J68)) | L68: =IF(COUNT(K$2:K68)<67,"",SUM(K$2:K68)) | M68: =IF(OR('Financial Basis'!B2="",L68=""),"",'Financial Basis'!B2+L68)
A69: 68 | B69: 2028-02-13 | K69: =IF(OR(N69<>"VERIFIED",COUNT(C69:J69)<8),"",SUM(C69:E69)-SUM(F69:J69)) | L69: =IF(COUNT(K$2:K69)<68,"",SUM(K$2:K69)) | M69: =IF(OR('Financial Basis'!B2="",L69=""),"",'Financial Basis'!B2+L69)
A70: 69 | B70: 2028-02-20 | K70: =IF(OR(N70<>"VERIFIED",COUNT(C70:J70)<8),"",SUM(C70:E70)-SUM(F70:J70)) | L70: =IF(COUNT(K$2:K70)<69,"",SUM(K$2:K70)) | M70: =IF(OR('Financial Basis'!B2="",L70=""),"",'Financial Basis'!B2+L70)
A71: 70 | B71: 2028-02-27 | K71: =IF(OR(N71<>"VERIFIED",COUNT(C71:J71)<8),"",SUM(C71:E71)-SUM(F71:J71)) | L71: =IF(COUNT(K$2:K71)<70,"",SUM(K$2:K71)) | M71: =IF(OR('Financial Basis'!B2="",L71=""),"",'Financial Basis'!B2+L71)
A72: 71 | B72: 2028-03-05 | K72: =IF(OR(N72<>"VERIFIED",COUNT(C72:J72)<8),"",SUM(C72:E72)-SUM(F72:J72)) | L72: =IF(COUNT(K$2:K72)<71,"",SUM(K$2:K72)) | M72: =IF(OR('Financial Basis'!B2="",L72=""),"",'Financial Basis'!B2+L72)
A73: 72 | B73: 2028-03-12 | K73: =IF(OR(N73<>"VERIFIED",COUNT(C73:J73)<8),"",SUM(C73:E73)-SUM(F73:J73)) | L73: =IF(COUNT(K$2:K73)<72,"",SUM(K$2:K73)) | M73: =IF(OR('Financial Basis'!B2="",L73=""),"",'Financial Basis'!B2+L73)
A74: 73 | B74: 2028-03-19 | K74: =IF(OR(N74<>"VERIFIED",COUNT(C74:J74)<8),"",SUM(C74:E74)-SUM(F74:J74)) | L74: =IF(COUNT(K$2:K74)<73,"",SUM(K$2:K74)) | M74: =IF(OR('Financial Basis'!B2="",L74=""),"",'Financial Basis'!B2+L74)
A75: 74 | B75: 2028-03-26 | K75: =IF(OR(N75<>"VERIFIED",COUNT(C75:J75)<8),"",SUM(C75:E75)-SUM(F75:J75)) | L75: =IF(COUNT(K$2:K75)<74,"",SUM(K$2:K75)) | M75: =IF(OR('Financial Basis'!B2="",L75=""),"",'Financial Basis'!B2+L75)
A76: 75 | B76: 2028-04-02 | K76: =IF(OR(N76<>"VERIFIED",COUNT(C76:J76)<8),"",SUM(C76:E76)-SUM(F76:J76)) | L76: =IF(COUNT(K$2:K76)<75,"",SUM(K$2:K76)) | M76: =IF(OR('Financial Basis'!B2="",L76=""),"",'Financial Basis'!B2+L76)
A77: 76 | B77: 2028-04-09 | K77: =IF(OR(N77<>"VERIFIED",COUNT(C77:J77)<8),"",SUM(C77:E77)-SUM(F77:J77)) | L77: =IF(COUNT(K$2:K77)<76,"",SUM(K$2:K77)) | M77: =IF(OR('Financial Basis'!B2="",L77=""),"",'Financial Basis'!B2+L77)
A78: 77 | B78: 2028-04-16 | K78: =IF(OR(N78<>"VERIFIED",COUNT(C78:J78)<8),"",SUM(C78:E78)-SUM(F78:J78)) | L78: =IF(COUNT(K$2:K78)<77,"",SUM(K$2:K78)) | M78: =IF(OR('Financial Basis'!B2="",L78=""),"",'Financial Basis'!B2+L78)
A79: 78 | B79: 2028-04-23 | K79: =IF(OR(N79<>"VERIFIED",COUNT(C79:J79)<8),"",SUM(C79:E79)-SUM(F79:J79)) | L79: =IF(COUNT(K$2:K79)<78,"",SUM(K$2:K79)) | M79: =IF(OR('Financial Basis'!B2="",L79=""),"",'Financial Basis'!B2+L79)
A80: 79 | B80: 2028-04-30 | K80: =IF(OR(N80<>"VERIFIED",COUNT(C80:J80)<8),"",SUM(C80:E80)-SUM(F80:J80)) | L80: =IF(COUNT(K$2:K80)<79,"",SUM(K$2:K80)) | M80: =IF(OR('Financial Basis'!B2="",L80=""),"",'Financial Basis'!B2+L80)
A81: 80 | B81: 2028-05-07 | K81: =IF(OR(N81<>"VERIFIED",COUNT(C81:J81)<8),"",SUM(C81:E81)-SUM(F81:J81)) | L81: =IF(COUNT(K$2:K81)<80,"",SUM(K$2:K81)) | M81: =IF(OR('Financial Basis'!B2="",L81=""),"",'Financial Basis'!B2+L81)
A82: 81 | B82: 2028-05-14 | K82: =IF(OR(N82<>"VERIFIED",COUNT(C82:J82)<8),"",SUM(C82:E82)-SUM(F82:J82)) | L82: =IF(COUNT(K$2:K82)<81,"",SUM(K$2:K82)) | M82: =IF(OR('Financial Basis'!B2="",L82=""),"",'Financial Basis'!B2+L82)
A83: 82 | B83: 2028-05-21 | K83: =IF(OR(N83<>"VERIFIED",COUNT(C83:J83)<8),"",SUM(C83:E83)-SUM(F83:J83)) | L83: =IF(COUNT(K$2:K83)<82,"",SUM(K$2:K83)) | M83: =IF(OR('Financial Basis'!B2="",L83=""),"",'Financial Basis'!B2+L83)
A84: 83 | B84: 2028-05-28 | K84: =IF(OR(N84<>"VERIFIED",COUNT(C84:J84)<8),"",SUM(C84:E84)-SUM(F84:J84)) | L84: =IF(COUNT(K$2:K84)<83,"",SUM(K$2:K84)) | M84: =IF(OR('Financial Basis'!B2="",L84=""),"",'Financial Basis'!B2+L84)
A85: 84 | B85: 2028-06-04 | K85: =IF(OR(N85<>"VERIFIED",COUNT(C85:J85)<8),"",SUM(C85:E85)-SUM(F85:J85)) | L85: =IF(COUNT(K$2:K85)<84,"",SUM(K$2:K85)) | M85: =IF(OR('Financial Basis'!B2="",L85=""),"",'Financial Basis'!B2+L85)
A86: 85 | B86: 2028-06-11 | K86: =IF(OR(N86<>"VERIFIED",COUNT(C86:J86)<8),"",SUM(C86:E86)-SUM(F86:J86)) | L86: =IF(COUNT(K$2:K86)<85,"",SUM(K$2:K86)) | M86: =IF(OR('Financial Basis'!B2="",L86=""),"",'Financial Basis'!B2+L86)
A87: 86 | B87: 2028-06-18 | K87: =IF(OR(N87<>"VERIFIED",COUNT(C87:J87)<8),"",SUM(C87:E87)-SUM(F87:J87)) | L87: =IF(COUNT(K$2:K87)<86,"",SUM(K$2:K87)) | M87: =IF(OR('Financial Basis'!B2="",L87=""),"",'Financial Basis'!B2+L87)
A88: 87 | B88: 2028-06-25 | K88: =IF(OR(N88<>"VERIFIED",COUNT(C88:J88)<8),"",SUM(C88:E88)-SUM(F88:J88)) | L88: =IF(COUNT(K$2:K88)<87,"",SUM(K$2:K88)) | M88: =IF(OR('Financial Basis'!B2="",L88=""),"",'Financial Basis'!B2+L88)
A89: 88 | B89: 2028-07-02 | K89: =IF(OR(N89<>"VERIFIED",COUNT(C89:J89)<8),"",SUM(C89:E89)-SUM(F89:J89)) | L89: =IF(COUNT(K$2:K89)<88,"",SUM(K$2:K89)) | M89: =IF(OR('Financial Basis'!B2="",L89=""),"",'Financial Basis'!B2+L89)
A90: 89 | B90: 2028-07-09 | K90: =IF(OR(N90<>"VERIFIED",COUNT(C90:J90)<8),"",SUM(C90:E90)-SUM(F90:J90)) | L90: =IF(COUNT(K$2:K90)<89,"",SUM(K$2:K90)) | M90: =IF(OR('Financial Basis'!B2="",L90=""),"",'Financial Basis'!B2+L90)
A91: 90 | B91: 2028-07-16 | K91: =IF(OR(N91<>"VERIFIED",COUNT(C91:J91)<8),"",SUM(C91:E91)-SUM(F91:J91)) | L91: =IF(COUNT(K$2:K91)<90,"",SUM(K$2:K91)) | M91: =IF(OR('Financial Basis'!B2="",L91=""),"",'Financial Basis'!B2+L91)
A92: 91 | B92: 2028-07-23 | K92: =IF(OR(N92<>"VERIFIED",COUNT(C92:J92)<8),"",SUM(C92:E92)-SUM(F92:J92)) | L92: =IF(COUNT(K$2:K92)<91,"",SUM(K$2:K92)) | M92: =IF(OR('Financial Basis'!B2="",L92=""),"",'Financial Basis'!B2+L92)
A93: 92 | B93: 2028-07-30 | K93: =IF(OR(N93<>"VERIFIED",COUNT(C93:J93)<8),"",SUM(C93:E93)-SUM(F93:J93)) | L93: =IF(COUNT(K$2:K93)<92,"",SUM(K$2:K93)) | M93: =IF(OR('Financial Basis'!B2="",L93=""),"",'Financial Basis'!B2+L93)
A94: 93 | B94: 2028-08-06 | K94: =IF(OR(N94<>"VERIFIED",COUNT(C94:J94)<8),"",SUM(C94:E94)-SUM(F94:J94)) | L94: =IF(COUNT(K$2:K94)<93,"",SUM(K$2:K94)) | M94: =IF(OR('Financial Basis'!B2="",L94=""),"",'Financial Basis'!B2+L94)
A95: 94 | B95: 2028-08-13 | K95: =IF(OR(N95<>"VERIFIED",COUNT(C95:J95)<8),"",SUM(C95:E95)-SUM(F95:J95)) | L95: =IF(COUNT(K$2:K95)<94,"",SUM(K$2:K95)) | M95: =IF(OR('Financial Basis'!B2="",L95=""),"",'Financial Basis'!B2+L95)
A96: 95 | B96: 2028-08-20 | K96: =IF(OR(N96<>"VERIFIED",COUNT(C96:J96)<8),"",SUM(C96:E96)-SUM(F96:J96)) | L96: =IF(COUNT(K$2:K96)<95,"",SUM(K$2:K96)) | M96: =IF(OR('Financial Basis'!B2="",L96=""),"",'Financial Basis'!B2+L96)
A97: 96 | B97: 2028-08-27 | K97: =IF(OR(N97<>"VERIFIED",COUNT(C97:J97)<8),"",SUM(C97:E97)-SUM(F97:J97)) | L97: =IF(COUNT(K$2:K97)<96,"",SUM(K$2:K97)) | M97: =IF(OR('Financial Basis'!B2="",L97=""),"",'Financial Basis'!B2+L97)
A98: 97 | B98: 2028-09-03 | K98: =IF(OR(N98<>"VERIFIED",COUNT(C98:J98)<8),"",SUM(C98:E98)-SUM(F98:J98)) | L98: =IF(COUNT(K$2:K98)<97,"",SUM(K$2:K98)) | M98: =IF(OR('Financial Basis'!B2="",L98=""),"",'Financial Basis'!B2+L98)
A99: 98 | B99: 2028-09-10 | K99: =IF(OR(N99<>"VERIFIED",COUNT(C99:J99)<8),"",SUM(C99:E99)-SUM(F99:J99)) | L99: =IF(COUNT(K$2:K99)<98,"",SUM(K$2:K99)) | M99: =IF(OR('Financial Basis'!B2="",L99=""),"",'Financial Basis'!B2+L99)
A100: 99 | B100: 2028-09-17 | K100: =IF(OR(N100<>"VERIFIED",COUNT(C100:J100)<8),"",SUM(C100:E100)-SUM(F100:J100)) | L100: =IF(COUNT(K$2:K100)<99,"",SUM(K$2:K100)) | M100: =IF(OR('Financial Basis'!B2="",L100=""),"",'Financial Basis'!B2+L100)
...

Sheet Change and Delay
A1: Event ID | B1: Date | C1: Source instruction | D1: Scope/bridge | E1: Notice deadline | F1: Owner | G1: Baseline activity | H1: Cause/attribution | I1: Cost evidence | J1: Schedule evidence | K1: Decision | L1: Status
L2: OPEN
L3: OPEN
L4: OPEN
L5: OPEN
L6: OPEN
L7: OPEN
L8: OPEN
L9: OPEN
L10: OPEN
L11: OPEN
L12: OPEN
L13: OPEN
... L21: OPEN

Sheet Turnover
A1: Bridge | B1: Boundary | C1: Required dossier | D1: Owner | E1: Blocking punch status | F1: Company acceptance | G1: Evidence
A2: ICW-ICG UD | B2: Structure/bearings | C2: As-built geometry, weld/NDT/coating, MTC, bearing setting and inspection | D2: Completions | E2: NOT ESTABLISHED | F2: NOT ACCEPTED
A3: ICW-ICG UD | B3: Services | C3: Isolation/transfer and accepted pressure/electrical/instrument functional tests as applicable | D3: Completions | E3: NOT ESTABLISHED | F3: NOT ACCEPTED
A4: ICW-ICG UD | B4: Scrap | C4: Removal/backload/transport and ONGC yard receipt | D4: Completions | E4: NOT ESTABLISHED | F4: NOT ACCEPTED
A5: ICW-ICG UD | B5: Documentation | C5: Native/as-built drawings/calculations/vendor data and accepted dossier index | D5: Completions | E5: NOT ESTABLISHED | F5: NOT ACCEPTED
A6: ICW-ICG LD | B6: Structure/bearings | C6: As-built geometry, weld/NDT/coating, MTC, bearing setting and inspection | D6: Completions | E6: NOT ESTABLISHED | F6: NOT ACCEPTED
A7: ICW-ICG LD | B7: Services | C7: Isolation/transfer and accepted pressure/electrical/instrument functional tests as applicable | D7: Completions | E7: NOT ESTABLISHED | F7: NOT ACCEPTED
A8: ICW-ICG LD | B8: Scrap | C8: Removal/backload/transport and ONGC yard receipt | D8: Completions | E8: NOT ESTABLISHED | F8: NOT ACCEPTED
A9: ICW-ICG LD | B9: Documentation | C9: Native/as-built drawings/calculations/vendor data and accepted dossier index | D9: Completions | E9: NOT ESTABLISHED | F9: NOT ACCEPTED
A10: ICG-ICP UD | B10: Structure/bearings | C10: As-built geometry, weld/NDT/coating, MTC, bearing setting and inspection | D10: Completions | E10: NOT ESTABLISHED | F10: NOT ACCEPTED
A11: ICG-ICP UD | B11: Services | C11: Isolation/transfer and accepted pressure/electrical/instrument functional tests as applicable | D11: Completions | E11: NOT ESTABLISHED | F11: NOT ACCEPTED
A12: ICG-ICP UD | B12: Scrap | C12: Removal/backload/transport and ONGC yard receipt | D12: Completions | E12: NOT ESTABLISHED | F12: NOT ACCEPTED
A13: ICG-ICP UD | B13: Documentation | C13: Native/as-built drawings/calculations/vendor data and accepted dossier index | D13: Completions | E13: NOT ESTABLISHED | F13: NOT ACCEPTED
... A41: SCA-SCF | B41: Documentation | C41: Native/as-built drawings/calculations/vendor data and accepted dossier index | D41: Completions | E41: NOT ESTABLISHED | F41: NOT ACCEPTED

Sheet 90 Day Mobilisation
A1: Relative day target | B1: Outcome | C1: Accountable | D1: Required evidence | E1: Status | F1: Dependency note
A2: 1 | B2: Confirm authorised mobilisation basis | C2: Contracts | D2: ActualNOA, funding ceiling and scope register | E2: OPEN | F2: No spending authority inferred
A3: 7 | B3: Appoint named team and data ownership | C3: Project Director | D3: RACI and availability | E3: OPEN | F3: Competence and retention of qualifying activities
A4: 15 | B4: Secure engineering/yard/marine offers | C4: Project Director | D4: Audited capacities and dated quotations | E4: OPEN | F4: Conditional reservations need authorised commercial decision
A5: 30 | B5: Accept survey/basis and validated schedule plan | C5: Engineering/Planning | D5: Survey/evidence and calendar/network review | E5: OPEN | F5: Target, not guarantee; field survey duration may control
A6: 45 | B6: First independently releasable engineering packages where achievable | C6: Engineering | D6: Signed accepted analysis/drawing/MTO release | E6: OPEN | F6: Not assumed in P14 base which releases later
A7: 60 | B7: Funded compliant procurement and released workfronts | C7: Procurement | D7: ApprovedPS/PO/release records | E7: OPEN | F7: No unapproved fabrication
A8: 75 | B8: Demonstrate accepted production and marine envelope | C8: Fabrication/Marine | D8: Actual productivity, quality and module/vessel studies | E8: OPEN | F8: Reforecast on evidence
A9: 90 | B9: Integrated feasibility and recovery decision | C9: Project Director | D9: CPM/resource/cash/release review | E9: OPEN | F9: Approve revised commitments only after verification

Sheet KPI and Escalation
A1: Metric | B1: Definition | C1: Proposed trigger | D1: Action | E1: Current value
A2: Release readiness | B2: All applicable evidence accepted for IWP | C2: Any mandatory hold open | D2: Do not release | E2: NO VERIFIED DATA
A3: Critical/near-critical delay | B3: Updated validated network vs approved milestone | C3: Negative target float or missed gate | D3: Recovery review; no invented actualfloat | E3: NO VERIFIED DATA
A4: Plan reliability | B4: Completed accepted weekly commitments / due commitments | C4: Below agreed target for2periods | D4: Constraint/root-cause review | E4: NO VERIFIED DATA
A5: Productivity | B5: Acceptedquantity / productivecrew-day | C5: Below validated estimate | D5: Check access, resources, rework and forecast | E5: NO VERIFIED DATA
A6: Quality rework | B6: Rejected/reworked quantity / inspected quantity | C6: Any structural rejection or recurring trend | D6: NCR and method review | E6: NO VERIFIED DATA
A7: Cash cover | B7: Funded available cash vs next13week obligations | C7: Forecast negative balance | D7: Finance/spending decision | E7: NO VERIFIED DATA
A8: Document review | B8: Age since valid submission vs applicable C8 period | C8: Overdue and driving release | D8: Escalate through agreed review route | E8: NO VERIFIED DATA
A9: Handover | B9: Accepted systems/dossiers vs due boundaries | C9: Blocking punch or dossier gap | D9: Dedicated closure owner | E9: NO VERIFIED DATA

Sheet Technical Queries
A1: Query | B1: Issue | C1: Source | D1: Required resolution | E1: Owner | F1: Release affected | G1: Status
A2: TQ01 | B2: BHS/SLQ fixed-versus-sliding bearing orientation differs between sources | C2: SOW/study versus criteria | D2: Confirm fixed point, sliding direction/travel, guide restraints and final bearing setting | E2: Structural/Company | F2: Bearing and supporting-deck design | G2: OPEN
A3: TQ02 | B3: Tender GA dimensions versus surveyed support/elevation geometry | C3: Combined1 p27,pp31–32,p36; original studies | D3: Verify centreline/gap/end-zone/extents and field tolerances; retain dimension conventions | E3: Survey/Structural | F3: Global model and shop details | G3: OPEN
A4: TQ03 | B4: ICW live-load resultant differs between report and model summary | C4: ICW preliminary report156.25kN versus SACS144.69kN | D4: Reconcile loaded area, load units and actual model loading; no error conclusion without model check | E4: Structural | F4: Load-case and calculation release | G4: OPEN
A5: TQ04 | B5: Camber based on DL versus genericL/200 source wording | C5: Criteria and three preliminary bridge studies | D5: Approve camber profile, fabrication tolerances, dead-load stage and field setting | E5: Structural/Fabrication | F5: Shop geometry | G5: OPEN
A6: TQ05 | B6: Procurement material grade and thickness not established by studyFy alone | C6: StudyFy50ksi and tender member references | D6: Specify grade, toughness/weldability, corrosion allowance and mill records for actual sections | E6: Structural/Procurement | F6: Material purchase | G6: OPEN
A7: TQ06 | B7: Actual corrosion loss/member joint condition | C7: Pre-engineering/NDT scope | D7: Use surveyed thickness/defects in capacity checks and repair details | E7: Survey/Structural | F7: Strengthening design | G7: OPEN
A8: TQ07 | B8: Wrap strengthening connection and staged capacity | C8: StructuralSOW addendumICG/ICP/BHS | D8: Check interface/weld/shear transfer, existing member condition, temporary stage and inspection access | E8: Structural | F8: Pre-install support release | G8: OPEN
A9: TQ08 | B9: Platform displacement and piping reactions | C9: Criteria movement/thrust; Combined3 p260 | D9: Agree platform translation/rotation/thermal movements and iterate piping/support/bearing reactions | E9: Structural/Piping | F9: Bearings/services/supports | G9: OPEN
A10: TQ09 | B10: Future piping allowance double counting | C10: Criteria operating/planned-future plus20% wording | D10: Separate known future loads from allowance and approve load schedule | E10: Piping/Structural | F10: Design-basis freeze | G10: OPEN
A11: TQ10 | B11: New drawing register34entries versus older38entries | C11: Combined1 pp3–5 | D11: Map omitted/renumbered sheets and revisions; do not infer scope deletion | E11: DocumentControl/Structural | F11: Drawing applicability baseline | G11: OPEN
A12: TQ11 | B12: ICW source GA registerRev0 versus titleRevA | C12: Combined1 p27 | D12: Obtain controlled issue identity and revision disposition | E12: DocumentControl | F12: Tender-to-detail mapping | G12: OPEN
... A16: TQ15 | B16: Discipline specification applicability and tie-in/test boundaries | C16: Combined1/2/3; bridge-specific scope | D16: Define actual piping/electrical/instrument/firewater/cable transfers and required tests; reject unrelated generic additions | E16: DisciplineLeads/Operations | F16: Service transfer and commissioning | G16: OPEN

Sheet Stage Integration
A1: Uploaded model | B1: P14 control | C1: Required correction or integration
A2: Stage27 | B2: Cost Commitments / Requirements / Daily Production | C2: Separate quantity/EV, certified billing and cash; maintain unknown inputs
A3: Stage28 | B3: Schedule285 / Calendars and Method | C3: Replace illustrative120activity chain with traceable integrated dependencies; actualL4detail still needs constructability
A4: Stage29 | B4: Schedule Scenarios / Resource Commitments | C4: Scenario capacity is uncommitted; verify bottlenecks and cost recovery
A5: Stage30 | B5: Workpack Readiness / Daily Production | C5: Verified quantities and accepted productivity required
A6: Stage31 | B6: Workpack Readiness / QA and Release Gates | C6: Screen alone cannot authorise work; require evidence and signed release
A7: Stage32 | B7: Productivity Forecast / Schedule285 | C7: Productive crew-day estimate is not calendarCPM; route remaining workdays to validated network
A8: Stage33 | B8: Risk Register / KPI and Escalation | C8: Track early-warning evidence and actual mitigation owner
A9: Stage34 | B9: CEO Decisions / Resource Commitments | C9: Use one source of date/cost/progress truth; no inconsistent parallel baselines
A10: Stage35 | B10: 90Day Mobilisation | C10: D45firstAFCis an objective; not demonstrated by baseline assumptions
A11: Volumes1–6 | B11: A–Z Execution Plan and linked registers | C11: Framework text remains planning; fill bridge-specific evidence and authority

Sheet Productivity Forecast
A1: Bridge | B1: Source indicative MT | C1: Approved baseline MT | D1: Accepted actual MT | E1: Productive crew-days | F1: Observed MT/productive crew-day | G1: Remaining approved MT | H1: Verified assigned crews | I1: Future productive utilisation0–1 | J1: Remaining productive workdays | K1: Updated CPMfinish input | L1: Status/evidence
A2: ICW-ICG UD | B2: 49 | F2: =IF(OR(D2="",E2="",E2<=0),"",D2/E2) | G2: =IF(OR(C2="",D2=""),"",MAX(0,C2-D2)) | J2: =IF(OR(F2="",F2<=0,G2="",H2="",H2<=0,I2="",I2<=0,I2>1),"",ROUNDUP(G2/F2/H2/I2,0)) | L2: No approved quantity/productivity yet
A3: ICW-ICG LD | B3: 122 | F3: =IF(OR(D3="",E3="",E3<=0),"",D3/E3) | G3: =IF(OR(C3="",D3=""),"",MAX(0,C3-D3)) | J3: =IF(OR(F3="",F3<=0,G3="",H3="",H3<=0,I3="",I3<=0,I3>1),"",ROUNDUP(G3/F3/H3/I3,0)) | L3: No approved quantity/productivity yet
A4: ICG-ICP UD | B4: 116 | F4: =IF(OR(D4="",E4="",E4<=0),"",D4/E4) | G4: =IF(OR(C4="",D4=""),"",MAX(0,C4-D4)) | J4: =IF(OR(F4="",F4<=0,G4="",H4="",H4<=0,I4="",I4<=0,I4>1),"",ROUNDUP(G4/F4/H4/I4,0)) | L4: No approved quantity/productivity yet
A5: ICG-ICP LD | B5: 160 | F5: =IF(OR(D5="",E5="",E5<=0),"",D5/E5) | G5: =IF(OR(C5="",D5=""),"",MAX(0,C5-D5)) | J5: =IF(OR(F5="",F5<=0,G5="",H5="",H5<=0,I5="",I5<=0,I5>1),"",ROUNDUP(G5/F5/H5/I5,0)) | L5: No approved quantity/productivity yet
A6: BHS-SLQ | B6: 282 | F6: =IF(OR(D6="",E6="",E6<=0),"",D6/E6) | G6: =IF(OR(C6="",D6=""),"",MAX(0,C6-D6)) | J6: =IF(OR(F6="",F6<=0,G6="",H6="",H6<=0,I6="",I6<=0,I6>1),"",ROUNDUP(G6/F6/H6/I6,0)) | L6: No approved quantity/productivity yet
A7: SLQ-WIS | B7: 91 | F7: =IF(OR(D7="",E7="",E7<=0),"",D7/E7) | G7: =IF(OR(C7="",D7=""),"",MAX(0,C7-D7)) | J7: =IF(OR(F7="",F7<=0,G7="",H7="",H7<=0,I7="",I7<=0,I7>1),"",ROUNDUP(G7/F7/H7/I7,0)) | L7: No approved quantity/productivity yet
A8: NQO-NQD | B8: 93 | F8: =IF(OR(D8="",E8="",E8<=0),"",D8/E8) | G8: =IF(OR(C8="",D8=""),"",MAX(0,C8-D8)) | J8: =IF(OR(F8="",F8<=0,G8="",H8="",H8<=0,I8="",I8<=0,I8>1),"",ROUNDUP(G8/F8/H8/I8,0)) | L8: No approved quantity/productivity yet
A9: WIN-NC | B9: 46 | F9: =IF(OR(D9="",E9="",E9<=0),"",D9/E9) | G9: =IF(OR(C9="",D9=""),"",MAX(0,C9-D9)) | J9: =IF(OR(F9="",F9<=0,G9="",H9="",H9<=0,I9="",I9<=0,I9>1),"",ROUNDUP(G9/F9/H9/I9,0)) | L9: No approved quantity/productivity yet
A10: SCA-SC1 | B10: 63 | F10: =IF(OR(D10="",E10="",E10<=0),"",D10/E10) | G10: =IF(OR(C10="",D10=""),"",MAX(0,C10-D10)) | J10: =IF(OR(F10="",F10<=0,G10="",H10="",H10<=0,I10="",I10<=0,I10>1),"",ROUNDUP(G10/F10/H10/I10,0)) | L10: No approved quantity/productivity yet
A11: SCA-SCF | B11: 119 | F11: =IF(OR(D11="",E11="",E11<=0),"",D11/E11) | G11: =IF(OR(C11="",D11=""),"",MAX(0,C11-D11)) | J11: =IF(OR(F11="",F11<=0,G11="",H11="",H11<=0,I11="",I11<=0,I11>1),"",ROUNDUP(G11/F11/H11/I11,0)) | L11: No approved quantity/productivity yet
